[
{"title": "勇往直前 守护生命（一线抗疫群英谱）（——记华中科技大学同济医学院附属同济医院“尖刀连”）", "url": "http://data.people.com.cn/rmrb/pd.html?qs=%7B%22cds%22%3A%5B%7B%22cdr%22%3A%22AND%22%2C%22cds%22%3A%5B%7B%22fld%22%3A%22title%22%2C%22cdr%22%3A%22OR%22%2C%22hlt%22%3A%22true%22%2C%22vlr%22%3A%22OR%22%2C%22val%22%3A%22%E5%90%8C%E6%B5%8E%E5%8C%BB%E5%AD%A6%E9%99%A2%22%7D%2C%7B%22fld%22%3A%22subTitle%22%2C%22cdr%22%3A%22OR%22%2C%22hlt%22%3A%22true%22%2C%22vlr%22%3A%22OR%22%2C%22val%22%3A%22%E5%90%8C%E6%B5%8E%E5%8C%BB%E5%AD%A6%E9%99%A2%22%7D%2C%7B%22fld%22%3A%22introTitle%22%2C%22cdr%22%3A%22OR%22%2C%22hlt%22%3A%22true%22%2C%22vlr%22%3A%22OR%22%2C%22val%22%3A%22%E5%90%8C%E6%B5%8E%E5%8C%BB%E5%AD%A6%E9%99%A2%22%7D%5D%7D%5D%2C%22obs%22%3A%5B%7B%22fld%22%3A%22dataTime%22%2C%22drt%22%3A%22DESC%22%7D%5D%7D&tr=A&pageNo=1&pageSize=500&position=0", "source": "2020年9月21日第6版"},
{"title": "近日，华中科技大学同济医学院招募了20名特殊的“病人”——— “标准化病人”引发争议", "url": "http://data.people.com.cn/rmrb/pd.html?qs=%7B%22cds%22%3A%5B%7B%22cdr%22%3A%22AND%22%2C%22cds%22%3A%5B%7B%22fld%22%3A%22title%22%2C%22cdr%22%3A%22OR%22%2C%22hlt%22%3A%22true%22%2C%22vlr%22%3A%22OR%22%2C%22val%22%3A%22%E5%90%8C%E6%B5%8E%E5%8C%BB%E5%AD%A6%E9%99%A2%22%7D%2C%7B%22fld%22%3A%22subTitle%22%2C%22cdr%22%3A%22OR%22%2C%22hlt%22%3A%22true%22%2C%22vlr%22%3A%22OR%22%2C%22val%22%3A%22%E5%90%8C%E6%B5%8E%E5%8C%BB%E5%AD%A6%E9%99%A2%22%7D%2C%7B%22fld%22%3A%22introTitle%22%2C%22cdr%22%3A%22OR%22%2C%22hlt%22%3A%22true%22%2C%22vlr%22%3A%22OR%22%2C%22val%22%3A%22%E5%90%8C%E6%B5%8E%E5%8C%BB%E5%AD%A6%E9%99%A2%22%7D%5D%7D%5D%2C%22obs%22%3A%5B%7B%22fld%22%3A%22dataTime%22%2C%22drt%22%3A%22DESC%22%7D%5D%7D&tr=A&pageNo=1&pageSize=500&position=1", "source": "2005年4月11日第5版"},
{"title": "华中工学院办班　培养专利法人才", "url": "http://data.people.com.cn/rmrb/pd.html?qs=%7B%22cds%22%3A%5B%7B%22cdr%22%3A%22AND%22%2C%22cds%22%3A%5B%7B%22fld%22%3A%22title%22%2C%22cdr%22%3A%22OR%22%2C%22hlt%22%3A%22true%22%2C%22vlr%22%3A%22OR%22%2C%22val%22%3A%22%E5%8D%8E%E4%B8%AD%E5%B7%A5%E5%AD%A6%E9%99%A2%22%7D%2C%7B%22fld%22%3A%22subTitle%22%2C%22cdr%22%3A%22OR%22%2C%22hlt%22%3A%22true%22%2C%22vlr%22%3A%22OR%22%2C%22val%22%3A%22%E5%8D%8E%E4%B8%AD%E5%B7%A5%E5%AD%A6%E9%99%A2%22%7D%2C%7B%22fld%22%3A%22introTitle%22%2C%22cdr%22%3A%22OR%22%2C%22hlt%22%3A%22true%22%2C%22vlr%22%3A%22OR%22%2C%22val%22%3A%22%E5%8D%8E%E4%B8%AD%E5%B7%A5%E5%AD%A6%E9%99%A2%22%7D%5D%7D%5D%2C%22obs%22%3A%5B%7B%22fld%22%3A%22dataTime%22%2C%22drt%22%3A%22DESC%22%7D%5D%7D&tr=A&pageNo=1&pageSize=500&position=0", "source": "1988年1月7日第3版"},
{"title": "华中工学院为基础课教师设奖", "url": "http://data.people.com.cn/rmrb/pd.html?qs=%7B%22cds%22%3A%5B%7B%22cdr%22%3A%22AND%22%2C%22cds%22%3A%5B%7B%22fld%22%3A%22title%22%2C%22cdr%22%3A%22OR%22%2C%22hlt%22%3A%22true%22%2C%22vlr%22%3A%22OR%22%2C%22val%22%3A%22%E5%8D%8E%E4%B8%AD%E5%B7%A5%E5%AD%A6%E9%99%A2%22%7D%2C%7B%22fld%22%3A%22subTitle%22%2C%22cdr%22%3A%22OR%22%2C%22hlt%22%3A%22true%22%2C%22vlr%22%3A%22OR%22%2C%22val%22%3A%22%E5%8D%8E%E4%B8%AD%E5%B7%A5%E5%AD%A6%E9%99%A2%22%7D%2C%7B%22fld%22%3A%22introTitle%22%2C%22cdr%22%3A%22OR%22%2C%22hlt%22%3A%22true%22%2C%22vlr%22%3A%22OR%22%2C%22val%22%3A%22%E5%8D%8E%E4%B8%AD%E5%B7%A5%E5%AD%A6%E9%99%A2%22%7D%5D%7D%5D%2C%22obs%22%3A%5B%7B%22fld%22%3A%22dataTime%22%2C%22drt%22%3A%22DESC%22%7D%5D%7D&tr=A&pageNo=1&pageSize=500&position=1", "source": "1987年12月28日第3版"},
{"title": "华中工学院培养跨学科人才", "url": "http://data.people.com.cn/rmrb/pd.html?qs=%7B%22cds%22%3A%5B%7B%22cdr%22%3A%22AND%22%2C%22cds%22%3A%5B%7B%22fld%22%3A%22title%22%2C%22cdr%22%3A%22OR%22%2C%22hlt%22%3A%22true%22%2C%22vlr%22%3A%22OR%22%2C%22val%22%3A%22%E5%8D%8E%E4%B8%AD%E5%B7%A5%E5%AD%A6%E9%99%A2%22%7D%2C%7B%22fld%22%3A%22subTitle%22%2C%22cdr%22%3A%22OR%22%2C%22hlt%22%3A%22true%22%2C%22vlr%22%3A%22OR%22%2C%22val%22%3A%22%E5%8D%8E%E4%B8%AD%E5%B7%A5%E5%AD%A6%E9%99%A2%22%7D%2C%7B%22fld%22%3A%22introTitle%22%2C%22cdr%22%3A%22OR%22%2C%22hlt%22%3A%22true%22%2C%22vlr%22%3A%22OR%22%2C%22val%22%3A%22%E5%8D%8E%E4%B8%AD%E5%B7%A5%E5%AD%A6%E9%99%A2%22%7D%5D%7D%5D%2C%22obs%22%3A%5B%7B%22fld%22%3A%22dataTime%22%2C%22drt%22%3A%22DESC%22%7D%5D%7D&tr=A&pageNo=1&pageSize=500&position=2", "source": "1987年11月10日第3版"},
{"title": "华中工学院注重共产主义远大理想教育 二千多大学生郑重递交入党申请书", "url": "http://data.people.com.cn/rmrb/pd.html?qs=%7B%22cds%22%3A%5B%7B%22cdr%22%3A%22AND%22%2C%22cds%22%3A%5B%7B%22fld%22%3A%22title%22%2C%22cdr%22%3A%22OR%22%2C%22hlt%22%3A%22true%22%2C%22vlr%22%3A%22OR%22%2C%22val%22%3A%22%E5%8D%8E%E4%B8%AD%E5%B7%A5%E5%AD%A6%E9%99%A2%22%7D%2C%7B%22fld%22%3A%22subTitle%22%2C%22cdr%22%3A%22OR%22%2C%22hlt%22%3A%22true%22%2C%22vlr%22%3A%22OR%22%2C%22val%22%3A%22%E5%8D%8E%E4%B8%AD%E5%B7%A5%E5%AD%A6%E9%99%A2%22%7D%2C%7B%22fld%22%3A%22introTitle%22%2C%22cdr%22%3A%22OR%22%2C%22hlt%22%3A%22true%22%2C%22vlr%22%3A%22OR%22%2C%22val%22%3A%22%E5%8D%8E%E4%B8%AD%E5%B7%A5%E5%AD%A6%E9%99%A2%22%7D%5D%7D%5D%2C%22obs%22%3A%5B%7B%22fld%22%3A%22dataTime%22%2C%22drt%22%3A%22DESC%22%7D%5D%7D&tr=A&pageNo=1&pageSize=500&position=3", "source": "1987年1月21日第3版"},
{"title": "华中工学院学生66项优秀科研成果获奖", "url": "http://data.people.com.cn/rmrb/pd.html?qs=%7B%22cds%22%3A%5B%7B%22cdr%22%3A%22AND%22%2C%22cds%22%3A%5B%7B%22fld%22%3A%22title%22%2C%22cdr%22%3A%22OR%22%2C%22hlt%22%3A%22true%22%2C%22vlr%22%3A%22OR%22%2C%22val%22%3A%22%E5%8D%8E%E4%B8%AD%E5%B7%A5%E5%AD%A6%E9%99%A2%22%7D%2C%7B%22fld%22%3A%22subTitle%22%2C%22cdr%22%3A%22OR%22%2C%22hlt%22%3A%22true%22%2C%22vlr%22%3A%22OR%22%2C%22val%22%3A%22%E5%8D%8E%E4%B8%AD%E5%B7%A5%E5%AD%A6%E9%99%A2%22%7D%2C%7B%22fld%22%3A%22introTitle%22%2C%22cdr%22%3A%22OR%22%2C%22hlt%22%3A%22true%22%2C%22vlr%22%3A%22OR%22%2C%22val%22%3A%22%E5%8D%8E%E4%B8%AD%E5%B7%A5%E5%AD%A6%E9%99%A2%22%7D%5D%7D%5D%2C%22obs%22%3A%5B%7B%22fld%22%3A%22dataTime%22%2C%22drt%22%3A%22DESC%22%7D%5D%7D&tr=A&pageNo=1&pageSize=500&position=4", "source": "1987年1月11日第1版"},
{"title": "二进校门的悲喜剧（罗健被劝退后再度考入华中工学院）", "url": "http://data.people.com.cn/rmrb/pd.html?qs=%7B%22cds%22%3A%5B%7B%22cdr%22%3A%22AND%22%2C%22cds%22%3A%5B%7B%22fld%22%3A%22title%22%2C%22cdr%22%3A%22OR%22%2C%22hlt%22%3A%22true%22%2C%22vlr%22%3A%22OR%22%2C%22val%22%3A%22%E5%8D%8E%E4%B8%AD%E5%B7%A5%E5%AD%A6%E9%99%A2%22%7D%2C%7B%22fld%22%3A%22subTitle%22%2C%22cdr%22%3A%22OR%22%2C%22hlt%22%3A%22true%22%2C%22vlr%22%3A%22OR%22%2C%22val%22%3A%22%E5%8D%8E%E4%B8%AD%E5%B7%A5%E5%AD%A6%E9%99%A2%22%7D%2C%7B%22fld%22%3A%22introTitle%22%2C%22cdr%22%3A%22OR%22%2C%22hlt%22%3A%22true%22%2C%22vlr%22%3A%22OR%22%2C%22val%22%3A%22%E5%8D%8E%E4%B8%AD%E5%B7%A5%E5%AD%A6%E9%99%A2%22%7D%5D%7D%5D%2C%22obs%22%3A%5B%7B%22fld%22%3A%22dataTime%22%2C%22drt%22%3A%22DESC%22%7D%5D%7D&tr=A&pageNo=1&pageSize=500&position=5", "source": "1986年9月12日第3版"},
{"title": "华中工学院党委积极做好侨务工作", "url": "http://data.people.com.cn/rmrb/pd.html?qs=%7B%22cds%22%3A%5B%7B%22cdr%22%3A%22AND%22%2C%22cds%22%3A%5B%7B%22fld%22%3A%22title%22%2C%22cdr%22%3A%22OR%22%2C%22hlt%22%3A%22true%22%2C%22vlr%22%3A%22OR%22%2C%22val%22%3A%22%E5%8D%8E%E4%B8%AD%E5%B7%A5%E5%AD%A6%E9%99%A2%22%7D%2C%7B%22fld%22%3A%22subTitle%22%2C%22cdr%22%3A%22OR%22%2C%22hlt%22%3A%22true%22%2C%22vlr%22%3A%22OR%22%2C%22val%22%3A%22%E5%8D%8E%E4%B8%AD%E5%B7%A5%E5%AD%A6%E9%99%A2%22%7D%2C%7B%22fld%22%3A%22introTitle%22%2C%22cdr%22%3A%22OR%22%2C%22hlt%22%3A%22true%22%2C%22vlr%22%3A%22OR%22%2C%22val%22%3A%22%E5%8D%8E%E4%B8%AD%E5%B7%A5%E5%AD%A6%E9%99%A2%22%7D%5D%7D%5D%2C%22obs%22%3A%5B%7B%22fld%22%3A%22dataTime%22%2C%22drt%22%3A%22DESC%22%7D%5D%7D&tr=A&pageNo=1&pageSize=500&position=6", "source": "1983年3月19日第4版"},
{"title": "华中工学院制出斩波型红外热象仪", "url": "http://data.people.com.cn/rmrb/pd.html?qs=%7B%22cds%22%3A%5B%7B%22cdr%22%3A%22AND%22%2C%22cds%22%3A%5B%7B%22fld%22%3A%22title%22%2C%22cdr%22%3A%22OR%22%2C%22hlt%22%3A%22true%22%2C%22vlr%22%3A%22OR%22%2C%22val%22%3A%22%E5%8D%8E%E4%B8%AD%E5%B7%A5%E5%AD%A6%E9%99%A2%22%7D%2C%7B%22fld%22%3A%22subTitle%22%2C%22cdr%22%3A%22OR%22%2C%22hlt%22%3A%22true%22%2C%22vlr%22%3A%22OR%22%2C%22val%22%3A%22%E5%8D%8E%E4%B8%AD%E5%B7%A5%E5%AD%A6%E9%99%A2%22%7D%2C%7B%22fld%22%3A%22introTitle%22%2C%22cdr%22%3A%22OR%22%2C%22hlt%22%3A%22true%22%2C%22vlr%22%3A%22OR%22%2C%22val%22%3A%22%E5%8D%8E%E4%B8%AD%E5%B7%A5%E5%AD%A6%E9%99%A2%22%7D%5D%7D%5D%2C%22obs%22%3A%5B%7B%22fld%22%3A%22dataTime%22%2C%22drt%22%3A%22DESC%22%7D%5D%7D&tr=A&pageNo=1&pageSize=500&position=7", "source": "1983年1月16日第1版"},
{"title": "华中工学院千余学生积极争取入党", "url": "http://data.people.com.cn/rmrb/pd.html?qs=%7B%22cds%22%3A%5B%7B%22cdr%22%3A%22AND%22%2C%22cds%22%3A%5B%7B%22fld%22%3A%22title%22%2C%22cdr%22%3A%22OR%22%2C%22hlt%22%3A%22true%22%2C%22vlr%22%3A%22OR%22%2C%22val%22%3A%22%E5%8D%8E%E4%B8%AD%E5%B7%A5%E5%AD%A6%E9%99%A2%22%7D%2C%7B%22fld%22%3A%22subTitle%22%2C%22cdr%22%3A%22OR%22%2C%22hlt%22%3A%22true%22%2C%22vlr%22%3A%22OR%22%2C%22val%22%3A%22%E5%8D%8E%E4%B8%AD%E5%B7%A5%E5%AD%A6%E9%99%A2%22%7D%2C%7B%22fld%22%3A%22introTitle%22%2C%22cdr%22%3A%22OR%22%2C%22hlt%22%3A%22true%22%2C%22vlr%22%3A%22OR%22%2C%22val%22%3A%22%E5%8D%8E%E4%B8%AD%E5%B7%A5%E5%AD%A6%E9%99%A2%22%7D%5D%7D%5D%2C%22obs%22%3A%5B%7B%22fld%22%3A%22dataTime%22%2C%22drt%22%3A%22DESC%22%7D%5D%7D&tr=A&pageNo=1&pageSize=500&position=8", "source": "1982年9月30日第5版"},
{"title": "华中工学院的“第二课堂”活动", "url": "http://data.people.com.cn/rmrb/pd.html?qs=%7B%22cds%22%3A%5B%7B%22cdr%22%3A%22AND%22%2C%22cds%22%3A%5B%7B%22fld%22%3A%22title%22%2C%22cdr%22%3A%22OR%22%2C%22hlt%22%3A%22true%22%2C%22vlr%22%3A%22OR%22%2C%22val%22%3A%22%E5%8D%8E%E4%B8%AD%E5%B7%A5%E5%AD%A6%E9%99%A2%22%7D%2C%7B%22fld%22%3A%22subTitle%22%2C%22cdr%22%3A%22OR%22%2C%22hlt%22%3A%22true%22%2C%22vlr%22%3A%22OR%22%2C%22val%22%3A%22%E5%8D%8E%E4%B8%AD%E5%B7%A5%E5%AD%A6%E9%99%A2%22%7D%2C%7B%22fld%22%3A%22introTitle%22%2C%22cdr%22%3A%22OR%22%2C%22hlt%22%3A%22true%22%2C%22vlr%22%3A%22OR%22%2C%22val%22%3A%22%E5%8D%8E%E4%B8%AD%E5%B7%A5%E5%AD%A6%E9%99%A2%22%7D%5D%7D%5D%2C%22obs%22%3A%5B%7B%22fld%22%3A%22dataTime%22%2C%22drt%22%3A%22DESC%22%7D%5D%7D&tr=A&pageNo=1&pageSize=500&position=9", "source": "1982年7月22日第3版"},
{"title": "华中工学院计算机系 抓住具体问题进行思想教育", "url": "http://data.people.com.cn/rmrb/pd.html?qs=%7B%22cds%22%3A%5B%7B%22cdr%22%3A%22AND%22%2C%22cds%22%3A%5B%7B%22fld%22%3A%22title%22%2C%22cdr%22%3A%22OR%22%2C%22hlt%22%3A%22true%22%2C%22vlr%22%3A%22OR%22%2C%22val%22%3A%22%E5%8D%8E%E4%B8%AD%E5%B7%A5%E5%AD%A6%E9%99%A2%22%7D%2C%7B%22fld%22%3A%22subTitle%22%2C%22cdr%22%3A%22OR%22%2C%22hlt%22%3A%22true%22%2C%22vlr%22%3A%22OR%22%2C%22val%22%3A%22%E5%8D%8E%E4%B8%AD%E5%B7%A5%E5%AD%A6%E9%99%A2%22%7D%2C%7B%22fld%22%3A%22introTitle%22%2C%22cdr%22%3A%22OR%22%2C%22hlt%22%3A%22true%22%2C%22vlr%22%3A%22OR%22%2C%22val%22%3A%22%E5%8D%8E%E4%B8%AD%E5%B7%A5%E5%AD%A6%E9%99%A2%22%7D%5D%7D%5D%2C%22obs%22%3A%5B%7B%22fld%22%3A%22dataTime%22%2C%22drt%22%3A%22DESC%22%7D%5D%7D&tr=A&pageNo=1&pageSize=500&position=10", "source": "1981年11月8日第3版"},
{"title": "华中工学院认真进行教育改革", "url": "http://data.people.com.cn/rmrb/pd.html?qs=%7B%22cds%22%3A%5B%7B%22cdr%22%3A%22AND%22%2C%22cds%22%3A%5B%7B%22fld%22%3A%22title%22%2C%22cdr%22%3A%22OR%22%2C%22hlt%22%3A%22true%22%2C%22vlr%22%3A%22OR%22%2C%22val%22%3A%22%E5%8D%8E%E4%B8%AD%E5%B7%A5%E5%AD%A6%E9%99%A2%22%7D%2C%7B%22fld%22%3A%22subTitle%22%2C%22cdr%22%3A%22OR%22%2C%22hlt%22%3A%22true%22%2C%22vlr%22%3A%22OR%22%2C%22val%22%3A%22%E5%8D%8E%E4%B8%AD%E5%B7%A5%E5%AD%A6%E9%99%A2%22%7D%2C%7B%22fld%22%3A%22introTitle%22%2C%22cdr%22%3A%22OR%22%2C%22hlt%22%3A%22true%22%2C%22vlr%22%3A%22OR%22%2C%22val%22%3A%22%E5%8D%8E%E4%B8%AD%E5%B7%A5%E5%AD%A6%E9%99%A2%22%7D%5D%7D%5D%2C%22obs%22%3A%5B%7B%22fld%22%3A%22dataTime%22%2C%22drt%22%3A%22DESC%22%7D%5D%7D&tr=A&pageNo=1&pageSize=500&position=11", "source": "1980年11月25日第3版"},
{"title": "华中工学院党委调动教师积极性", "url": "http://data.people.com.cn/rmrb/pd.html?qs=%7B%22cds%22%3A%5B%7B%22cdr%22%3A%22AND%22%2C%22cds%22%3A%5B%7B%22fld%22%3A%22title%22%2C%22cdr%22%3A%22OR%22%2C%22hlt%22%3A%22true%22%2C%22vlr%22%3A%22OR%22%2C%22val%22%3A%22%E5%8D%8E%E4%B8%AD%E5%B7%A5%E5%AD%A6%E9%99%A2%22%7D%2C%7B%22fld%22%3A%22subTitle%22%2C%22cdr%22%3A%22OR%22%2C%22hlt%22%3A%22true%22%2C%22vlr%22%3A%22OR%22%2C%22val%22%3A%22%E5%8D%8E%E4%B8%AD%E5%B7%A5%E5%AD%A6%E9%99%A2%22%7D%2C%7B%22fld%22%3A%22introTitle%22%2C%22cdr%22%3A%22OR%22%2C%22hlt%22%3A%22true%22%2C%22vlr%22%3A%22OR%22%2C%22val%22%3A%22%E5%8D%8E%E4%B8%AD%E5%B7%A5%E5%AD%A6%E9%99%A2%22%7D%5D%7D%5D%2C%22obs%22%3A%5B%7B%22fld%22%3A%22dataTime%22%2C%22drt%22%3A%22DESC%22%7D%5D%7D&tr=A&pageNo=1&pageSize=500&position=12", "source": "1979年12月20日第3版"},
{"title": "工人大学生回厂后发挥很大作用　　从华中工学院毕业的一批工人大学生，在生产岗位上，运用在大学所学的理论知识解决生产实际问题，受到工厂领导和群众的赞扬", "url": "http://data.people.com.cn/rmrb/pd.html?qs=%7B%22cds%22%3A%5B%7B%22cdr%22%3A%22AND%22%2C%22cds%22%3A%5B%7B%22fld%22%3A%22title%22%2C%22cdr%22%3A%22OR%22%2C%22hlt%22%3A%22true%22%2C%22vlr%22%3A%22OR%22%2C%22val%22%3A%22%E5%8D%8E%E4%B8%AD%E5%B7%A5%E5%AD%A6%E9%99%A2%22%7D%2C%7B%22fld%22%3A%22subTitle%22%2C%22cdr%22%3A%22OR%22%2C%22hlt%22%3A%22true%22%2C%22vlr%22%3A%22OR%22%2C%22val%22%3A%22%E5%8D%8E%E4%B8%AD%E5%B7%A5%E5%AD%A6%E9%99%A2%22%7D%2C%7B%22fld%22%3A%22introTitle%22%2C%22cdr%22%3A%22OR%22%2C%22hlt%22%3A%22true%22%2C%22vlr%22%3A%22OR%22%2C%22val%22%3A%22%E5%8D%8E%E4%B8%AD%E5%B7%A5%E5%AD%A6%E9%99%A2%22%7D%5D%7D%5D%2C%22obs%22%3A%5B%7B%22fld%22%3A%22dataTime%22%2C%22drt%22%3A%22DESC%22%7D%5D%7D&tr=A&pageNo=1&pageSize=500&position=13", "source": "1973年3月19日第1版"},
{"title": "巴沙尼团长在华中工学院讲话驳斥帝国主义对中国的诬蔑  盛赞我社会主义建设的成就", "url": "http://data.people.com.cn/rmrb/pd.html?qs=%7B%22cds%22%3A%5B%7B%22cdr%22%3A%22AND%22%2C%22cds%22%3A%5B%7B%22fld%22%3A%22title%22%2C%22cdr%22%3A%22OR%22%2C%22hlt%22%3A%22true%22%2C%22vlr%22%3A%22OR%22%2C%22val%22%3A%22%E5%8D%8E%E4%B8%AD%E5%B7%A5%E5%AD%A6%E9%99%A2%22%7D%2C%7B%22fld%22%3A%22subTitle%22%2C%22cdr%22%3A%22OR%22%2C%22hlt%22%3A%22true%22%2C%22vlr%22%3A%22OR%22%2C%22val%22%3A%22%E5%8D%8E%E4%B8%AD%E5%B7%A5%E5%AD%A6%E9%99%A2%22%7D%2C%7B%22fld%22%3A%22introTitle%22%2C%22cdr%22%3A%22OR%22%2C%22hlt%22%3A%22true%22%2C%22vlr%22%3A%22OR%22%2C%22val%22%3A%22%E5%8D%8E%E4%B8%AD%E5%B7%A5%E5%AD%A6%E9%99%A2%22%7D%5D%7D%5D%2C%22obs%22%3A%5B%7B%22fld%22%3A%22dataTime%22%2C%22drt%22%3A%22DESC%22%7D%5D%7D&tr=A&pageNo=1&pageSize=500&position=14", "source": "1963年11月8日第4版"},
{"title": "主动了解实习要求　帮助制造修理设备　华中工学院附设工厂积极服务教学", "url": "http://data.people.com.cn/rmrb/pd.html?qs=%7B%22cds%22%3A%5B%7B%22cdr%22%3A%22AND%22%2C%22cds%22%3A%5B%7B%22fld%22%3A%22title%22%2C%22cdr%22%3A%22OR%22%2C%22hlt%22%3A%22true%22%2C%22vlr%22%3A%22OR%22%2C%22val%22%3A%22%E5%8D%8E%E4%B8%AD%E5%B7%A5%E5%AD%A6%E9%99%A2%22%7D%2C%7B%22fld%22%3A%22subTitle%22%2C%22cdr%22%3A%22OR%22%2C%22hlt%22%3A%22true%22%2C%22vlr%22%3A%22OR%22%2C%22val%22%3A%22%E5%8D%8E%E4%B8%AD%E5%B7%A5%E5%AD%A6%E9%99%A2%22%7D%2C%7B%22fld%22%3A%22introTitle%22%2C%22cdr%22%3A%22OR%22%2C%22hlt%22%3A%22true%22%2C%22vlr%22%3A%22OR%22%2C%22val%22%3A%22%E5%8D%8E%E4%B8%AD%E5%B7%A5%E5%AD%A6%E9%99%A2%22%7D%5D%7D%5D%2C%22obs%22%3A%5B%7B%22fld%22%3A%22dataTime%22%2C%22drt%22%3A%22DESC%22%7D%5D%7D&tr=A&pageNo=1&pageSize=500&position=15", "source": "1962年3月24日第2版"},
{"title": "武汉重型机床厂和华中工学院等联合办学的果实　    业余大学首届毕业生成绩优良", "url": "http://data.people.com.cn/rmrb/pd.html?qs=%7B%22cds%22%3A%5B%7B%22cdr%22%3A%22AND%22%2C%22cds%22%3A%5B%7B%22fld%22%3A%22title%22%2C%22cdr%22%3A%22OR%22%2C%22hlt%22%3A%22true%22%2C%22vlr%22%3A%22OR%22%2C%22val%22%3A%22%E5%8D%8E%E4%B8%AD%E5%B7%A5%E5%AD%A6%E9%99%A2%22%7D%2C%7B%22fld%22%3A%22subTitle%22%2C%22cdr%22%3A%22OR%22%2C%22hlt%22%3A%22true%22%2C%22vlr%22%3A%22OR%22%2C%22val%22%3A%22%E5%8D%8E%E4%B8%AD%E5%B7%A5%E5%AD%A6%E9%99%A2%22%7D%2C%7B%22fld%22%3A%22introTitle%22%2C%22cdr%22%3A%22OR%22%2C%22hlt%22%3A%22true%22%2C%22vlr%22%3A%22OR%22%2C%22val%22%3A%22%E5%8D%8E%E4%B8%AD%E5%B7%A5%E5%AD%A6%E9%99%A2%22%7D%5D%7D%5D%2C%22obs%22%3A%5B%7B%22fld%22%3A%22dataTime%22%2C%22drt%22%3A%22DESC%22%7D%5D%7D&tr=A&pageNo=1&pageSize=500&position=16", "source": "1961年12月13日第4版"},
{"title": "藏书乃财富  闲置实可惜  武汉医学院图书馆向社会开放　    铁路是动脉  奔流应不息  粤桂湘三省军用线让地方使用（今日首都和各省市区报纸要目）", "url": "http://data.people.com.cn/rmrb/pd.html?qs=%7B%22cds%22%3A%5B%7B%22cdr%22%3A%22AND%22%2C%22cds%22%3A%5B%7B%22fld%22%3A%22title%22%2C%22cdr%22%3A%22OR%22%2C%22hlt%22%3A%22true%22%2C%22vlr%22%3A%22OR%22%2C%22val%22%3A%22%E6%AD%A6%E6%B1%89%E5%8C%BB%E5%AD%A6%E9%99%A2%22%7D%2C%7B%22fld%22%3A%22subTitle%22%2C%22cdr%22%3A%22OR%22%2C%22hlt%22%3A%22true%22%2C%22vlr%22%3A%22OR%22%2C%22val%22%3A%22%E6%AD%A6%E6%B1%89%E5%8C%BB%E5%AD%A6%E9%99%A2%22%7D%2C%7B%22fld%22%3A%22introTitle%22%2C%22cdr%22%3A%22OR%22%2C%22hlt%22%3A%22true%22%2C%22vlr%22%3A%22OR%22%2C%22val%22%3A%22%E6%AD%A6%E6%B1%89%E5%8C%BB%E5%AD%A6%E9%99%A2%22%7D%5D%7D%5D%2C%22obs%22%3A%5B%7B%22fld%22%3A%22dataTime%22%2C%22drt%22%3A%22DESC%22%7D%5D%7D&tr=A&pageNo=1&pageSize=500&position=0", "source": "1985年3月14日第3版"},
{"title": "武汉医学院向从教五十周年以上的教师颁发荣誉证书", "url": "http://data.people.com.cn/rmrb/pd.html?qs=%7B%22cds%22%3A%5B%7B%22cdr%22%3A%22AND%22%2C%22cds%22%3A%5B%7B%22fld%22%3A%22title%22%2C%22cdr%22%3A%22OR%22%2C%22hlt%22%3A%22true%22%2C%22vlr%22%3A%22OR%22%2C%22val%22%3A%22%E6%AD%A6%E6%B1%89%E5%8C%BB%E5%AD%A6%E9%99%A2%22%7D%2C%7B%22fld%22%3A%22subTitle%22%2C%22cdr%22%3A%22OR%22%2C%22hlt%22%3A%22true%22%2C%22vlr%22%3A%22OR%22%2C%22val%22%3A%22%E6%AD%A6%E6%B1%89%E5%8C%BB%E5%AD%A6%E9%99%A2%22%7D%2C%7B%22fld%22%3A%22introTitle%22%2C%22cdr%22%3A%22OR%22%2C%22hlt%22%3A%22true%22%2C%22vlr%22%3A%22OR%22%2C%22val%22%3A%22%E6%AD%A6%E6%B1%89%E5%8C%BB%E5%AD%A6%E9%99%A2%22%7D%5D%7D%5D%2C%22obs%22%3A%5B%7B%22fld%22%3A%22dataTime%22%2C%22drt%22%3A%22DESC%22%7D%5D%7D&tr=A&pageNo=1&pageSize=500&position=1", "source": "1985年2月9日第3版"},
{"title": "北京医学院、武汉医学院和西德埃森综合大学校际协议实施方案在京签字", "url": "http://data.people.com.cn/rmrb/pd.html?qs=%7B%22cds%22%3A%5B%7B%22cdr%22%3A%22AND%22%2C%22cds%22%3A%5B%7B%22fld%22%3A%22title%22%2C%22cdr%22%3A%22OR%22%2C%22hlt%22%3A%22true%22%2C%22vlr%22%3A%22OR%22%2C%22val%22%3A%22%E6%AD%A6%E6%B1%89%E5%8C%BB%E5%AD%A6%E9%99%A2%22%7D%2C%7B%22fld%22%3A%22subTitle%22%2C%22cdr%22%3A%22OR%22%2C%22hlt%22%3A%22true%22%2C%22vlr%22%3A%22OR%22%2C%22val%22%3A%22%E6%AD%A6%E6%B1%89%E5%8C%BB%E5%AD%A6%E9%99%A2%22%7D%2C%7B%22fld%22%3A%22introTitle%22%2C%22cdr%22%3A%22OR%22%2C%22hlt%22%3A%22true%22%2C%22vlr%22%3A%22OR%22%2C%22val%22%3A%22%E6%AD%A6%E6%B1%89%E5%8C%BB%E5%AD%A6%E9%99%A2%22%7D%5D%7D%5D%2C%22obs%22%3A%5B%7B%22fld%22%3A%22dataTime%22%2C%22drt%22%3A%22DESC%22%7D%5D%7D&tr=A&pageNo=1&pageSize=500&position=2", "source": "1981年3月23日第4版"},
{"title": "武汉医学院第一附属医院等单位 研制成功强效降压新药", "url": "http://data.people.com.cn/rmrb/pd.html?qs=%7B%22cds%22%3A%5B%7B%22cdr%22%3A%22AND%22%2C%22cds%22%3A%5B%7B%22fld%22%3A%22title%22%2C%22cdr%22%3A%22OR%22%2C%22hlt%22%3A%22true%22%2C%22vlr%22%3A%22OR%22%2C%22val%22%3A%22%E6%AD%A6%E6%B1%89%E5%8C%BB%E5%AD%A6%E9%99%A2%22%7D%2C%7B%22fld%22%3A%22subTitle%22%2C%22cdr%22%3A%22OR%22%2C%22hlt%22%3A%22true%22%2C%22vlr%22%3A%22OR%22%2C%22val%22%3A%22%E6%AD%A6%E6%B1%89%E5%8C%BB%E5%AD%A6%E9%99%A2%22%7D%2C%7B%22fld%22%3A%22introTitle%22%2C%22cdr%22%3A%22OR%22%2C%22hlt%22%3A%22true%22%2C%22vlr%22%3A%22OR%22%2C%22val%22%3A%22%E6%AD%A6%E6%B1%89%E5%8C%BB%E5%AD%A6%E9%99%A2%22%7D%5D%7D%5D%2C%22obs%22%3A%5B%7B%22fld%22%3A%22dataTime%22%2C%22drt%22%3A%22DESC%22%7D%5D%7D&tr=A&pageNo=1&pageSize=500&position=3", "source": "1980年3月1日第4版"},
{"title": "开门办学同改变农村医疗卫生面貌相结合　　　武汉医学院教育革命深入发展", "url": "http://data.people.com.cn/rmrb/pd.html?qs=%7B%22cds%22%3A%5B%7B%22cdr%22%3A%22AND%22%2C%22cds%22%3A%5B%7B%22fld%22%3A%22title%22%2C%22cdr%22%3A%22OR%22%2C%22hlt%22%3A%22true%22%2C%22vlr%22%3A%22OR%22%2C%22val%22%3A%22%E6%AD%A6%E6%B1%89%E5%8C%BB%E5%AD%A6%E9%99%A2%22%7D%2C%7B%22fld%22%3A%22subTitle%22%2C%22cdr%22%3A%22OR%22%2C%22hlt%22%3A%22true%22%2C%22vlr%22%3A%22OR%22%2C%22val%22%3A%22%E6%AD%A6%E6%B1%89%E5%8C%BB%E5%AD%A6%E9%99%A2%22%7D%2C%7B%22fld%22%3A%22introTitle%22%2C%22cdr%22%3A%22OR%22%2C%22hlt%22%3A%22true%22%2C%22vlr%22%3A%22OR%22%2C%22val%22%3A%22%E6%AD%A6%E6%B1%89%E5%8C%BB%E5%AD%A6%E9%99%A2%22%7D%5D%7D%5D%2C%22obs%22%3A%5B%7B%22fld%22%3A%22dataTime%22%2C%22drt%22%3A%22DESC%22%7D%5D%7D&tr=A&pageNo=1&pageSize=500&position=4", "source": "1974年2月20日第4版"},
{"title": "武汉医学院附属第一医院　　中西医结合治疗骨与关节损伤", "url": "http://data.people.com.cn/rmrb/pd.html?qs=%7B%22cds%22%3A%5B%7B%22cdr%22%3A%22AND%22%2C%22cds%22%3A%5B%7B%22fld%22%3A%22title%22%2C%22cdr%22%3A%22OR%22%2C%22hlt%22%3A%22true%22%2C%22vlr%22%3A%22OR%22%2C%22val%22%3A%22%E6%AD%A6%E6%B1%89%E5%8C%BB%E5%AD%A6%E9%99%A2%22%7D%2C%7B%22fld%22%3A%22subTitle%22%2C%22cdr%22%3A%22OR%22%2C%22hlt%22%3A%22true%22%2C%22vlr%22%3A%22OR%22%2C%22val%22%3A%22%E6%AD%A6%E6%B1%89%E5%8C%BB%E5%AD%A6%E9%99%A2%22%7D%2C%7B%22fld%22%3A%22introTitle%22%2C%22cdr%22%3A%22OR%22%2C%22hlt%22%3A%22true%22%2C%22vlr%22%3A%22OR%22%2C%22val%22%3A%22%E6%AD%A6%E6%B1%89%E5%8C%BB%E5%AD%A6%E9%99%A2%22%7D%5D%7D%5D%2C%22obs%22%3A%5B%7B%22fld%22%3A%22dataTime%22%2C%22drt%22%3A%22DESC%22%7D%5D%7D&tr=A&pageNo=1&pageSize=500&position=5", "source": "1973年7月11日第2版"},
{"title": "武汉医学院第一附属医院医务人员听毛主席的话深入农村　　虚心接受贫下中农再教育　全心全意为贫下中农治病", "url": "http://data.people.com.cn/rmrb/pd.html?qs=%7B%22cds%22%3A%5B%7B%22cdr%22%3A%22AND%22%2C%22cds%22%3A%5B%7B%22fld%22%3A%22title%22%2C%22cdr%22%3A%22OR%22%2C%22hlt%22%3A%22true%22%2C%22vlr%22%3A%22OR%22%2C%22val%22%3A%22%E6%AD%A6%E6%B1%89%E5%8C%BB%E5%AD%A6%E9%99%A2%22%7D%2C%7B%22fld%22%3A%22subTitle%22%2C%22cdr%22%3A%22OR%22%2C%22hlt%22%3A%22true%22%2C%22vlr%22%3A%22OR%22%2C%22val%22%3A%22%E6%AD%A6%E6%B1%89%E5%8C%BB%E5%AD%A6%E9%99%A2%22%7D%2C%7B%22fld%22%3A%22introTitle%22%2C%22cdr%22%3A%22OR%22%2C%22hlt%22%3A%22true%22%2C%22vlr%22%3A%22OR%22%2C%22val%22%3A%22%E6%AD%A6%E6%B1%89%E5%8C%BB%E5%AD%A6%E9%99%A2%22%7D%5D%7D%5D%2C%22obs%22%3A%5B%7B%22fld%22%3A%22dataTime%22%2C%22drt%22%3A%22DESC%22%7D%5D%7D&tr=A&pageNo=1&pageSize=500&position=6", "source": "1970年4月15日第2版"},
{"title": "革命大批判促进了人的思想革命化　　驻武汉医学院第一附属医院工人、解放军毛泽东思想宣　　传队领导全院群众狠批大叛徒刘少奇的反革命修正主义　　医疗卫生路线，有效地提高了广大医务人员的阶级斗争　　、两条路线斗争觉悟和为人民服务的自觉性", "url": "http://data.people.com.cn/rmrb/pd.html?qs=%7B%22cds%22%3A%5B%7B%22cdr%22%3A%22AND%22%2C%22cds%22%3A%5B%7B%22fld%22%3A%22title%22%2C%22cdr%22%3A%22OR%22%2C%22hlt%22%3A%22true%22%2C%22vlr%22%3A%22OR%22%2C%22val%22%3A%22%E6%AD%A6%E6%B1%89%E5%8C%BB%E5%AD%A6%E9%99%A2%22%7D%2C%7B%22fld%22%3A%22subTitle%22%2C%22cdr%22%3A%22OR%22%2C%22hlt%22%3A%22true%22%2C%22vlr%22%3A%22OR%22%2C%22val%22%3A%22%E6%AD%A6%E6%B1%89%E5%8C%BB%E5%AD%A6%E9%99%A2%22%7D%2C%7B%22fld%22%3A%22introTitle%22%2C%22cdr%22%3A%22OR%22%2C%22hlt%22%3A%22true%22%2C%22vlr%22%3A%22OR%22%2C%22val%22%3A%22%E6%AD%A6%E6%B1%89%E5%8C%BB%E5%AD%A6%E9%99%A2%22%7D%5D%7D%5D%2C%22obs%22%3A%5B%7B%22fld%22%3A%22dataTime%22%2C%22drt%22%3A%22DESC%22%7D%5D%7D&tr=A&pageNo=1&pageSize=500&position=7", "source": "1969年6月22日第1版"},
{"title": "切除腹主动脉瘤　移植塑料血管　　武汉医学院第二附属医院施行了一次成功手术", "url": "http://data.people.com.cn/rmrb/pd.html?qs=%7B%22cds%22%3A%5B%7B%22cdr%22%3A%22AND%22%2C%22cds%22%3A%5B%7B%22fld%22%3A%22title%22%2C%22cdr%22%3A%22OR%22%2C%22hlt%22%3A%22true%22%2C%22vlr%22%3A%22OR%22%2C%22val%22%3A%22%E6%AD%A6%E6%B1%89%E5%8C%BB%E5%AD%A6%E9%99%A2%22%7D%2C%7B%22fld%22%3A%22subTitle%22%2C%22cdr%22%3A%22OR%22%2C%22hlt%22%3A%22true%22%2C%22vlr%22%3A%22OR%22%2C%22val%22%3A%22%E6%AD%A6%E6%B1%89%E5%8C%BB%E5%AD%A6%E9%99%A2%22%7D%2C%7B%22fld%22%3A%22introTitle%22%2C%22cdr%22%3A%22OR%22%2C%22hlt%22%3A%22true%22%2C%22vlr%22%3A%22OR%22%2C%22val%22%3A%22%E6%AD%A6%E6%B1%89%E5%8C%BB%E5%AD%A6%E9%99%A2%22%7D%5D%7D%5D%2C%22obs%22%3A%5B%7B%22fld%22%3A%22dataTime%22%2C%22drt%22%3A%22DESC%22%7D%5D%7D&tr=A&pageNo=1&pageSize=500&position=8", "source": "1962年3月5日第1版"},
{"title": "武汉医学院第二附属医院　    老中医帮助西医系统掌握中医学术", "url": "http://data.people.com.cn/rmrb/pd.html?qs=%7B%22cds%22%3A%5B%7B%22cdr%22%3A%22AND%22%2C%22cds%22%3A%5B%7B%22fld%22%3A%22title%22%2C%22cdr%22%3A%22OR%22%2C%22hlt%22%3A%22true%22%2C%22vlr%22%3A%22OR%22%2C%22val%22%3A%22%E6%AD%A6%E6%B1%89%E5%8C%BB%E5%AD%A6%E9%99%A2%22%7D%2C%7B%22fld%22%3A%22subTitle%22%2C%22cdr%22%3A%22OR%22%2C%22hlt%22%3A%22true%22%2C%22vlr%22%3A%22OR%22%2C%22val%22%3A%22%E6%AD%A6%E6%B1%89%E5%8C%BB%E5%AD%A6%E9%99%A2%22%7D%2C%7B%22fld%22%3A%22introTitle%22%2C%22cdr%22%3A%22OR%22%2C%22hlt%22%3A%22true%22%2C%22vlr%22%3A%22OR%22%2C%22val%22%3A%22%E6%AD%A6%E6%B1%89%E5%8C%BB%E5%AD%A6%E9%99%A2%22%7D%5D%7D%5D%2C%22obs%22%3A%5B%7B%22fld%22%3A%22dataTime%22%2C%22drt%22%3A%22DESC%22%7D%5D%7D&tr=A&pageNo=1&pageSize=500&position=9", "source": "1961年12月14日第4版"},
{"title": "给农民除疾病　给自己添知识（武汉医学院和湖北医学院师生下乡除害灭病）", "url": "http://data.people.com.cn/rmrb/pd.html?qs=%7B%22cds%22%3A%5B%7B%22cdr%22%3A%22AND%22%2C%22cds%22%3A%5B%7B%22fld%22%3A%22title%22%2C%22cdr%22%3A%22OR%22%2C%22hlt%22%3A%22true%22%2C%22vlr%22%3A%22OR%22%2C%22val%22%3A%22%E6%AD%A6%E6%B1%89%E5%8C%BB%E5%AD%A6%E9%99%A2%22%7D%2C%7B%22fld%22%3A%22subTitle%22%2C%22cdr%22%3A%22OR%22%2C%22hlt%22%3A%22true%22%2C%22vlr%22%3A%22OR%22%2C%22val%22%3A%22%E6%AD%A6%E6%B1%89%E5%8C%BB%E5%AD%A6%E9%99%A2%22%7D%2C%7B%22fld%22%3A%22introTitle%22%2C%22cdr%22%3A%22OR%22%2C%22hlt%22%3A%22true%22%2C%22vlr%22%3A%22OR%22%2C%22val%22%3A%22%E6%AD%A6%E6%B1%89%E5%8C%BB%E5%AD%A6%E9%99%A2%22%7D%5D%7D%5D%2C%22obs%22%3A%5B%7B%22fld%22%3A%22dataTime%22%2C%22drt%22%3A%22DESC%22%7D%5D%7D&tr=A&pageNo=1&pageSize=500&position=10", "source": "1959年3月19日第6版"},
{"title": "对高温作业的劳动卫生  武汉医学院教学工作者提出不少改进意见", "url": "http://data.people.com.cn/rmrb/pd.html?qs=%7B%22cds%22%3A%5B%7B%22cdr%22%3A%22AND%22%2C%22cds%22%3A%5B%7B%22fld%22%3A%22title%22%2C%22cdr%22%3A%22OR%22%2C%22hlt%22%3A%22true%22%2C%22vlr%22%3A%22OR%22%2C%22val%22%3A%22%E6%AD%A6%E6%B1%89%E5%8C%BB%E5%AD%A6%E9%99%A2%22%7D%2C%7B%22fld%22%3A%22subTitle%22%2C%22cdr%22%3A%22OR%22%2C%22hlt%22%3A%22true%22%2C%22vlr%22%3A%22OR%22%2C%22val%22%3A%22%E6%AD%A6%E6%B1%89%E5%8C%BB%E5%AD%A6%E9%99%A2%22%7D%2C%7B%22fld%22%3A%22introTitle%22%2C%22cdr%22%3A%22OR%22%2C%22hlt%22%3A%22true%22%2C%22vlr%22%3A%22OR%22%2C%22val%22%3A%22%E6%AD%A6%E6%B1%89%E5%8C%BB%E5%AD%A6%E9%99%A2%22%7D%5D%7D%5D%2C%22obs%22%3A%5B%7B%22fld%22%3A%22dataTime%22%2C%22drt%22%3A%22DESC%22%7D%5D%7D&tr=A&pageNo=1&pageSize=500&position=11", "source": "1956年8月26日第7版"},
{"title": "关心师生生活  多方促进教学　    华中工学院重新安排科学研究和劳动时间师生生活紧张、愉快、活泼　    大连工学院采取专职队伍和群众相结合办法改进食堂工作受到赞扬", "url": "http://data.people.com.cn/rmrb/pd.html?qs=%7B%22cds%22%3A%5B%7B%22cdr%22%3A%22AND%22%2C%22cds%22%3A%5B%7B%22fld%22%3A%22title%22%2C%22cdr%22%3A%22OR%22%2C%22hlt%22%3A%22true%22%2C%22vlr%22%3A%22OR%22%2C%22val%22%3A%22%E5%8D%8E%E4%B8%AD%E5%B7%A5%E5%AD%A6%E9%99%A2%22%7D%2C%7B%22fld%22%3A%22subTitle%22%2C%22cdr%22%3A%22OR%22%2C%22hlt%22%3A%22true%22%2C%22vlr%22%3A%22OR%22%2C%22val%22%3A%22%E5%8D%8E%E4%B8%AD%E5%B7%A5%E5%AD%A6%E9%99%A2%22%7D%2C%7B%22fld%22%3A%22introTitle%22%2C%22cdr%22%3A%22OR%22%2C%22hlt%22%3A%22true%22%2C%22vlr%22%3A%22OR%22%2C%22val%22%3A%22%E5%8D%8E%E4%B8%AD%E5%B7%A5%E5%AD%A6%E9%99%A2%22%7D%5D%7D%5D%2C%22obs%22%3A%5B%7B%22fld%22%3A%22dataTime%22%2C%22drt%22%3A%22DESC%22%7D%5D%7D&tr=A&pageNo=1&pageSize=500&position=17", "source": "1960年12月19日第4版"},
{"title": "华中工学院大冶钢厂广泛协作", "url": "http://data.people.com.cn/rmrb/pd.html?qs=%7B%22cds%22%3A%5B%7B%22cdr%22%3A%22AND%22%2C%22cds%22%3A%5B%7B%22fld%22%3A%22title%22%2C%22cdr%22%3A%22OR%22%2C%22hlt%22%3A%22true%22%2C%22vlr%22%3A%22OR%22%2C%22val%22%3A%22%E5%8D%8E%E4%B8%AD%E5%B7%A5%E5%AD%A6%E9%99%A2%22%7D%2C%7B%22fld%22%3A%22subTitle%22%2C%22cdr%22%3A%22OR%22%2C%22hlt%22%3A%22true%22%2C%22vlr%22%3A%22OR%22%2C%22val%22%3A%22%E5%8D%8E%E4%B8%AD%E5%B7%A5%E5%AD%A6%E9%99%A2%22%7D%2C%7B%22fld%22%3A%22introTitle%22%2C%22cdr%22%3A%22OR%22%2C%22hlt%22%3A%22true%22%2C%22vlr%22%3A%22OR%22%2C%22val%22%3A%22%E5%8D%8E%E4%B8%AD%E5%B7%A5%E5%AD%A6%E9%99%A2%22%7D%5D%7D%5D%2C%22obs%22%3A%5B%7B%22fld%22%3A%22dataTime%22%2C%22drt%22%3A%22DESC%22%7D%5D%7D&tr=A&pageNo=1&pageSize=500&position=18", "source": "1959年12月11日第4版"},
{"title": "华中工学院下厂采集研究课题", "url": "http://data.people.com.cn/rmrb/pd.html?qs=%7B%22cds%22%3A%5B%7B%22cdr%22%3A%22AND%22%2C%22cds%22%3A%5B%7B%22fld%22%3A%22title%22%2C%22cdr%22%3A%22OR%22%2C%22hlt%22%3A%22true%22%2C%22vlr%22%3A%22OR%22%2C%22val%22%3A%22%E5%8D%8E%E4%B8%AD%E5%B7%A5%E5%AD%A6%E9%99%A2%22%7D%2C%7B%22fld%22%3A%22subTitle%22%2C%22cdr%22%3A%22OR%22%2C%22hlt%22%3A%22true%22%2C%22vlr%22%3A%22OR%22%2C%22val%22%3A%22%E5%8D%8E%E4%B8%AD%E5%B7%A5%E5%AD%A6%E9%99%A2%22%7D%2C%7B%22fld%22%3A%22introTitle%22%2C%22cdr%22%3A%22OR%22%2C%22hlt%22%3A%22true%22%2C%22vlr%22%3A%22OR%22%2C%22val%22%3A%22%E5%8D%8E%E4%B8%AD%E5%B7%A5%E5%AD%A6%E9%99%A2%22%7D%5D%7D%5D%2C%22obs%22%3A%5B%7B%22fld%22%3A%22dataTime%22%2C%22drt%22%3A%22DESC%22%7D%5D%7D&tr=A&pageNo=1&pageSize=500&position=19", "source": "1959年12月5日第4版"},
{"title": "生产、科学研究紧密结合国家需要（华中工学院提高了教学质量支援了生产大跃进）", "url": "http://data.people.com.cn/rmrb/pd.html?qs=%7B%22cds%22%3A%5B%7B%22cdr%22%3A%22AND%22%2C%22cds%22%3A%5B%7B%22fld%22%3A%22title%22%2C%22cdr%22%3A%22OR%22%2C%22hlt%22%3A%22true%22%2C%22vlr%22%3A%22OR%22%2C%22val%22%3A%22%E5%8D%8E%E4%B8%AD%E5%B7%A5%E5%AD%A6%E9%99%A2%22%7D%2C%7B%22fld%22%3A%22subTitle%22%2C%22cdr%22%3A%22OR%22%2C%22hlt%22%3A%22true%22%2C%22vlr%22%3A%22OR%22%2C%22val%22%3A%22%E5%8D%8E%E4%B8%AD%E5%B7%A5%E5%AD%A6%E9%99%A2%22%7D%2C%7B%22fld%22%3A%22introTitle%22%2C%22cdr%22%3A%22OR%22%2C%22hlt%22%3A%22true%22%2C%22vlr%22%3A%22OR%22%2C%22val%22%3A%22%E5%8D%8E%E4%B8%AD%E5%B7%A5%E5%AD%A6%E9%99%A2%22%7D%5D%7D%5D%2C%22obs%22%3A%5B%7B%22fld%22%3A%22dataTime%22%2C%22drt%22%3A%22DESC%22%7D%5D%7D&tr=A&pageNo=1&pageSize=500&position=20", "source": "1959年2月17日第6版"},
{"title": "教学、科学研究和生产紧密结合（华中工学院、杭州大学提高了教学质量）", "url": "http://data.people.com.cn/rmrb/pd.html?qs=%7B%22cds%22%3A%5B%7B%22cdr%22%3A%22AND%22%2C%22cds%22%3A%5B%7B%22fld%22%3A%22title%22%2C%22cdr%22%3A%22OR%22%2C%22hlt%22%3A%22true%22%2C%22vlr%22%3A%22OR%22%2C%22val%22%3A%22%E5%8D%8E%E4%B8%AD%E5%B7%A5%E5%AD%A6%E9%99%A2%22%7D%2C%7B%22fld%22%3A%22subTitle%22%2C%22cdr%22%3A%22OR%22%2C%22hlt%22%3A%22true%22%2C%22vlr%22%3A%22OR%22%2C%22val%22%3A%22%E5%8D%8E%E4%B8%AD%E5%B7%A5%E5%AD%A6%E9%99%A2%22%7D%2C%7B%22fld%22%3A%22introTitle%22%2C%22cdr%22%3A%22OR%22%2C%22hlt%22%3A%22true%22%2C%22vlr%22%3A%22OR%22%2C%22val%22%3A%22%E5%8D%8E%E4%B8%AD%E5%B7%A5%E5%AD%A6%E9%99%A2%22%7D%5D%7D%5D%2C%22obs%22%3A%5B%7B%22fld%22%3A%22dataTime%22%2C%22drt%22%3A%22DESC%22%7D%5D%7D&tr=A&pageNo=1&pageSize=500&position=21", "source": "1959年1月29日第6版"},
{"title": "华中工学院附属工厂教职工 制成竹木质离心机", "url": "http://data.people.com.cn/rmrb/pd.html?qs=%7B%22cds%22%3A%5B%7B%22cdr%22%3A%22AND%22%2C%22cds%22%3A%5B%7B%22fld%22%3A%22title%22%2C%22cdr%22%3A%22OR%22%2C%22hlt%22%3A%22true%22%2C%22vlr%22%3A%22OR%22%2C%22val%22%3A%22%E5%8D%8E%E4%B8%AD%E5%B7%A5%E5%AD%A6%E9%99%A2%22%7D%2C%7B%22fld%22%3A%22subTitle%22%2C%22cdr%22%3A%22OR%22%2C%22hlt%22%3A%22true%22%2C%22vlr%22%3A%22OR%22%2C%22val%22%3A%22%E5%8D%8E%E4%B8%AD%E5%B7%A5%E5%AD%A6%E9%99%A2%22%7D%2C%7B%22fld%22%3A%22introTitle%22%2C%22cdr%22%3A%22OR%22%2C%22hlt%22%3A%22true%22%2C%22vlr%22%3A%22OR%22%2C%22val%22%3A%22%E5%8D%8E%E4%B8%AD%E5%B7%A5%E5%AD%A6%E9%99%A2%22%7D%5D%7D%5D%2C%22obs%22%3A%5B%7B%22fld%22%3A%22dataTime%22%2C%22drt%22%3A%22DESC%22%7D%5D%7D&tr=A&pageNo=1&pageSize=500&position=22", "source": "1958年6月27日第7版"},
{"title": "教育必须结合生产（华中工学院开展勤工俭学大辩论）", "url": "http://data.people.com.cn/rmrb/pd.html?qs=%7B%22cds%22%3A%5B%7B%22cdr%22%3A%22AND%22%2C%22cds%22%3A%5B%7B%22fld%22%3A%22title%22%2C%22cdr%22%3A%22OR%22%2C%22hlt%22%3A%22true%22%2C%22vlr%22%3A%22OR%22%2C%22val%22%3A%22%E5%8D%8E%E4%B8%AD%E5%B7%A5%E5%AD%A6%E9%99%A2%22%7D%2C%7B%22fld%22%3A%22subTitle%22%2C%22cdr%22%3A%22OR%22%2C%22hlt%22%3A%22true%22%2C%22vlr%22%3A%22OR%22%2C%22val%22%3A%22%E5%8D%8E%E4%B8%AD%E5%B7%A5%E5%AD%A6%E9%99%A2%22%7D%2C%7B%22fld%22%3A%22introTitle%22%2C%22cdr%22%3A%22OR%22%2C%22hlt%22%3A%22true%22%2C%22vlr%22%3A%22OR%22%2C%22val%22%3A%22%E5%8D%8E%E4%B8%AD%E5%B7%A5%E5%AD%A6%E9%99%A2%22%7D%5D%7D%5D%2C%22obs%22%3A%5B%7B%22fld%22%3A%22dataTime%22%2C%22drt%22%3A%22DESC%22%7D%5D%7D&tr=A&pageNo=1&pageSize=500&position=23", "source": "1958年6月23日第7版"},
{"title": "从实践中革新教学（华中工学院全力支援地方工业）", "url": "http://data.people.com.cn/rmrb/pd.html?qs=%7B%22cds%22%3A%5B%7B%22cdr%22%3A%22AND%22%2C%22cds%22%3A%5B%7B%22fld%22%3A%22title%22%2C%22cdr%22%3A%22OR%22%2C%22hlt%22%3A%22true%22%2C%22vlr%22%3A%22OR%22%2C%22val%22%3A%22%E5%8D%8E%E4%B8%AD%E5%B7%A5%E5%AD%A6%E9%99%A2%22%7D%2C%7B%22fld%22%3A%22subTitle%22%2C%22cdr%22%3A%22OR%22%2C%22hlt%22%3A%22true%22%2C%22vlr%22%3A%22OR%22%2C%22val%22%3A%22%E5%8D%8E%E4%B8%AD%E5%B7%A5%E5%AD%A6%E9%99%A2%22%7D%2C%7B%22fld%22%3A%22introTitle%22%2C%22cdr%22%3A%22OR%22%2C%22hlt%22%3A%22true%22%2C%22vlr%22%3A%22OR%22%2C%22val%22%3A%22%E5%8D%8E%E4%B8%AD%E5%B7%A5%E5%AD%A6%E9%99%A2%22%7D%5D%7D%5D%2C%22obs%22%3A%5B%7B%22fld%22%3A%22dataTime%22%2C%22drt%22%3A%22DESC%22%7D%5D%7D&tr=A&pageNo=1&pageSize=500&position=24", "source": "1958年5月7日第7版"},
{"title": "华中工学院反浪费反保守做得好", "url": "http://data.people.com.cn/rmrb/pd.html?qs=%7B%22cds%22%3A%5B%7B%22cdr%22%3A%22AND%22%2C%22cds%22%3A%5B%7B%22fld%22%3A%22title%22%2C%22cdr%22%3A%22OR%22%2C%22hlt%22%3A%22true%22%2C%22vlr%22%3A%22OR%22%2C%22val%22%3A%22%E5%8D%8E%E4%B8%AD%E5%B7%A5%E5%AD%A6%E9%99%A2%22%7D%2C%7B%22fld%22%3A%22subTitle%22%2C%22cdr%22%3A%22OR%22%2C%22hlt%22%3A%22true%22%2C%22vlr%22%3A%22OR%22%2C%22val%22%3A%22%E5%8D%8E%E4%B8%AD%E5%B7%A5%E5%AD%A6%E9%99%A2%22%7D%2C%7B%22fld%22%3A%22introTitle%22%2C%22cdr%22%3A%22OR%22%2C%22hlt%22%3A%22true%22%2C%22vlr%22%3A%22OR%22%2C%22val%22%3A%22%E5%8D%8E%E4%B8%AD%E5%B7%A5%E5%AD%A6%E9%99%A2%22%7D%5D%7D%5D%2C%22obs%22%3A%5B%7B%22fld%22%3A%22dataTime%22%2C%22drt%22%3A%22DESC%22%7D%5D%7D&tr=A&pageNo=1&pageSize=500&position=25", "source": "1958年3月5日第7版"},
{"title": "我武汉同济医科大学荣获“歌德塑像”奖", "url": "http://data.people.com.cn/rmrb/pd.html?qs=%7B%22cds%22%3A%5B%7B%22cdr%22%3A%22AND%22%2C%22cds%22%3A%5B%7B%22fld%22%3A%22title%22%2C%22cdr%22%3A%22OR%22%2C%22hlt%22%3A%22true%22%2C%22vlr%22%3A%22OR%22%2C%22val%22%3A%22%E5%90%8C%E6%B5%8E%E5%8C%BB%E7%A7%91%E5%A4%A7%E5%AD%A6%22%7D%2C%7B%22fld%22%3A%22subTitle%22%2C%22cdr%22%3A%22OR%22%2C%22hlt%22%3A%22true%22%2C%22vlr%22%3A%22OR%22%2C%22val%22%3A%22%E5%90%8C%E6%B5%8E%E5%8C%BB%E7%A7%91%E5%A4%A7%E5%AD%A6%22%7D%2C%7B%22fld%22%3A%22introTitle%22%2C%22cdr%22%3A%22OR%22%2C%22hlt%22%3A%22true%22%2C%22vlr%22%3A%22OR%22%2C%22val%22%3A%22%E5%90%8C%E6%B5%8E%E5%8C%BB%E7%A7%91%E5%A4%A7%E5%AD%A6%22%7D%5D%7D%5D%2C%22obs%22%3A%5B%7B%22fld%22%3A%22dataTime%22%2C%22drt%22%3A%22DESC%22%7D%5D%7D&tr=A&pageNo=1&pageSize=500&position=13", "source": "1997年8月26日第7版"},
{"title": "同济医科大学喜庆九十华诞", "url": "http://data.people.com.cn/rmrb/pd.html?qs=%7B%22cds%22%3A%5B%7B%22cdr%22%3A%22AND%22%2C%22cds%22%3A%5B%7B%22fld%22%3A%22title%22%2C%22cdr%22%3A%22OR%22%2C%22hlt%22%3A%22true%22%2C%22vlr%22%3A%22OR%22%2C%22val%22%3A%22%E5%90%8C%E6%B5%8E%E5%8C%BB%E7%A7%91%E5%A4%A7%E5%AD%A6%22%7D%2C%7B%22fld%22%3A%22subTitle%22%2C%22cdr%22%3A%22OR%22%2C%22hlt%22%3A%22true%22%2C%22vlr%22%3A%22OR%22%2C%22val%22%3A%22%E5%90%8C%E6%B5%8E%E5%8C%BB%E7%A7%91%E5%A4%A7%E5%AD%A6%22%7D%2C%7B%22fld%22%3A%22introTitle%22%2C%22cdr%22%3A%22OR%22%2C%22hlt%22%3A%22true%22%2C%22vlr%22%3A%22OR%22%2C%22val%22%3A%22%E5%90%8C%E6%B5%8E%E5%8C%BB%E7%A7%91%E5%A4%A7%E5%AD%A6%22%7D%5D%7D%5D%2C%22obs%22%3A%5B%7B%22fld%22%3A%22dataTime%22%2C%22drt%22%3A%22DESC%22%7D%5D%7D&tr=A&pageNo=1&pageSize=500&position=14", "source": "1997年5月26日第1版"},
{"title": "同济医科大学附属协和医院五年获四十五项科研成果", "url": "http://data.people.com.cn/rmrb/pd.html?qs=%7B%22cds%22%3A%5B%7B%22cdr%22%3A%22AND%22%2C%22cds%22%3A%5B%7B%22fld%22%3A%22title%22%2C%22cdr%22%3A%22OR%22%2C%22hlt%22%3A%22true%22%2C%22vlr%22%3A%22OR%22%2C%22val%22%3A%22%E5%90%8C%E6%B5%8E%E5%8C%BB%E7%A7%91%E5%A4%A7%E5%AD%A6%22%7D%2C%7B%22fld%22%3A%22subTitle%22%2C%22cdr%22%3A%22OR%22%2C%22hlt%22%3A%22true%22%2C%22vlr%22%3A%22OR%22%2C%22val%22%3A%22%E5%90%8C%E6%B5%8E%E5%8C%BB%E7%A7%91%E5%A4%A7%E5%AD%A6%22%7D%2C%7B%22fld%22%3A%22introTitle%22%2C%22cdr%22%3A%22OR%22%2C%22hlt%22%3A%22true%22%2C%22vlr%22%3A%22OR%22%2C%22val%22%3A%22%E5%90%8C%E6%B5%8E%E5%8C%BB%E7%A7%91%E5%A4%A7%E5%AD%A6%22%7D%5D%7D%5D%2C%22obs%22%3A%5B%7B%22fld%22%3A%22dataTime%22%2C%22drt%22%3A%22DESC%22%7D%5D%7D&tr=A&pageNo=1&pageSize=500&position=19", "source": "1985年12月29日第3版"},
{"title": "华中科技大学制止一起假冒招生行为", "url": "http://data.people.com.cn/rmrb/pd.html?qs=%7B%22cds%22%3A%5B%7B%22cdr%22%3A%22AND%22%2C%22cds%22%3A%5B%7B%22fld%22%3A%22title%22%2C%22cdr%22%3A%22OR%22%2C%22hlt%22%3A%22true%22%2C%22vlr%22%3A%22OR%22%2C%22val%22%3A%22%E5%8D%8E%E4%B8%AD%E7%90%86%E5%B7%A5%E5%A4%A7%E5%AD%A6%22%7D%2C%7B%22fld%22%3A%22subTitle%22%2C%22cdr%22%3A%22OR%22%2C%22hlt%22%3A%22true%22%2C%22vlr%22%3A%22OR%22%2C%22val%22%3A%22%E5%8D%8E%E4%B8%AD%E7%90%86%E5%B7%A5%E5%A4%A7%E5%AD%A6%22%7D%2C%7B%22fld%22%3A%22introTitle%22%2C%22cdr%22%3A%22OR%22%2C%22hlt%22%3A%22true%22%2C%22vlr%22%3A%22OR%22%2C%22val%22%3A%22%E5%8D%8E%E4%B8%AD%E7%90%86%E5%B7%A5%E5%A4%A7%E5%AD%A6%22%7D%5D%7D%5D%2C%22obs%22%3A%5B%7B%22fld%22%3A%22dataTime%22%2C%22drt%22%3A%22DESC%22%7D%5D%7D&tr=A&pageNo=1&pageSize=500&position=6", "source": "2012年7月4日第8版"},
{"title": "华中科技大学60岁校庆走起“学术范”", "url": "http://data.people.com.cn/rmrb/pd.html?qs=%7B%22cds%22%3A%5B%7B%22cdr%22%3A%22AND%22%2C%22cds%22%3A%5B%7B%22fld%22%3A%22title%22%2C%22cdr%22%3A%22OR%22%2C%22hlt%22%3A%22true%22%2C%22vlr%22%3A%22OR%22%2C%22val%22%3A%22%E5%8D%8E%E4%B8%AD%E7%90%86%E5%B7%A5%E5%A4%A7%E5%AD%A6%22%7D%2C%7B%22fld%22%3A%22subTitle%22%2C%22cdr%22%3A%22OR%22%2C%22hlt%22%3A%22true%22%2C%22vlr%22%3A%22OR%22%2C%22val%22%3A%22%E5%8D%8E%E4%B8%AD%E7%90%86%E5%B7%A5%E5%A4%A7%E5%AD%A6%22%7D%2C%7B%22fld%22%3A%22introTitle%22%2C%22cdr%22%3A%22OR%22%2C%22hlt%22%3A%22true%22%2C%22vlr%22%3A%22OR%22%2C%22val%22%3A%22%E5%8D%8E%E4%B8%AD%E7%90%86%E5%B7%A5%E5%A4%A7%E5%AD%A6%22%7D%5D%7D%5D%2C%22obs%22%3A%5B%7B%22fld%22%3A%22dataTime%22%2C%22drt%22%3A%22DESC%22%7D%5D%7D&tr=A&pageNo=1&pageSize=500&position=8", "source": "2012年3月2日第12版"},
{"title": "华中科技大学创新教育激发活力", "url": "http://data.people.com.cn/rmrb/pd.html?qs=%7B%22cds%22%3A%5B%7B%22cdr%22%3A%22AND%22%2C%22cds%22%3A%5B%7B%22fld%22%3A%22title%22%2C%22cdr%22%3A%22OR%22%2C%22hlt%22%3A%22true%22%2C%22vlr%22%3A%22OR%22%2C%22val%22%3A%22%E5%8D%8E%E4%B8%AD%E7%90%86%E5%B7%A5%E5%A4%A7%E5%AD%A6%22%7D%2C%7B%22fld%22%3A%22subTitle%22%2C%22cdr%22%3A%22OR%22%2C%22hlt%22%3A%22true%22%2C%22vlr%22%3A%22OR%22%2C%22val%22%3A%22%E5%8D%8E%E4%B8%AD%E7%90%86%E5%B7%A5%E5%A4%A7%E5%AD%A6%22%7D%2C%7B%22fld%22%3A%22introTitle%22%2C%22cdr%22%3A%22OR%22%2C%22hlt%22%3A%22true%22%2C%22vlr%22%3A%22OR%22%2C%22val%22%3A%22%E5%8D%8E%E4%B8%AD%E7%90%86%E5%B7%A5%E5%A4%A7%E5%AD%A6%22%7D%5D%7D%5D%2C%22obs%22%3A%5B%7B%22fld%22%3A%22dataTime%22%2C%22drt%22%3A%22DESC%22%7D%5D%7D&tr=A&pageNo=1&pageSize=500&position=13", "source": "2010年5月23日第1版"},
{"title": "华中科技大学　党支部建在班上", "url": "http://data.people.com.cn/rmrb/pd.html?qs=%7B%22cds%22%3A%5B%7B%22cdr%22%3A%22AND%22%2C%22cds%22%3A%5B%7B%22fld%22%3A%22title%22%2C%22cdr%22%3A%22OR%22%2C%22hlt%22%3A%22true%22%2C%22vlr%22%3A%22OR%22%2C%22val%22%3A%22%E5%8D%8E%E4%B8%AD%E7%90%86%E5%B7%A5%E5%A4%A7%E5%AD%A6%22%7D%2C%7B%22fld%22%3A%22subTitle%22%2C%22cdr%22%3A%22OR%22%2C%22hlt%22%3A%22true%22%2C%22vlr%22%3A%22OR%22%2C%22val%22%3A%22%E5%8D%8E%E4%B8%AD%E7%90%86%E5%B7%A5%E5%A4%A7%E5%AD%A6%22%7D%2C%7B%22fld%22%3A%22introTitle%22%2C%22cdr%22%3A%22OR%22%2C%22hlt%22%3A%22true%22%2C%22vlr%22%3A%22OR%22%2C%22val%22%3A%22%E5%8D%8E%E4%B8%AD%E7%90%86%E5%B7%A5%E5%A4%A7%E5%AD%A6%22%7D%5D%7D%5D%2C%22obs%22%3A%5B%7B%22fld%22%3A%22dataTime%22%2C%22drt%22%3A%22DESC%22%7D%5D%7D&tr=A&pageNo=1&pageSize=500&position=21", "source": "2003年10月28日第11版"},
{"title": "华中科技大学庆祝建校50周年", "url": "http://data.people.com.cn/rmrb/pd.html?qs=%7B%22cds%22%3A%5B%7B%22cdr%22%3A%22AND%22%2C%22cds%22%3A%5B%7B%22fld%22%3A%22title%22%2C%22cdr%22%3A%22OR%22%2C%22hlt%22%3A%22true%22%2C%22vlr%22%3A%22OR%22%2C%22val%22%3A%22%E5%8D%8E%E4%B8%AD%E7%90%86%E5%B7%A5%E5%A4%A7%E5%AD%A6%22%7D%2C%7B%22fld%22%3A%22subTitle%22%2C%22cdr%22%3A%22OR%22%2C%22hlt%22%3A%22true%22%2C%22vlr%22%3A%22OR%22%2C%22val%22%3A%22%E5%8D%8E%E4%B8%AD%E7%90%86%E5%B7%A5%E5%A4%A7%E5%AD%A6%22%7D%2C%7B%22fld%22%3A%22introTitle%22%2C%22cdr%22%3A%22OR%22%2C%22hlt%22%3A%22true%22%2C%22vlr%22%3A%22OR%22%2C%22val%22%3A%22%E5%8D%8E%E4%B8%AD%E7%90%86%E5%B7%A5%E5%A4%A7%E5%AD%A6%22%7D%5D%7D%5D%2C%22obs%22%3A%5B%7B%22fld%22%3A%22dataTime%22%2C%22drt%22%3A%22DESC%22%7D%5D%7D&tr=A&pageNo=1&pageSize=500&position=24", "source": "2003年10月9日第11版"},
{"title": "我国再获大学领先奖（华中理工大学CIMS技术达国际先进水平）", "url": "http://data.people.com.cn/rmrb/pd.html?qs=%7B%22cds%22%3A%5B%7B%22cdr%22%3A%22AND%22%2C%22cds%22%3A%5B%7B%22fld%22%3A%22title%22%2C%22cdr%22%3A%22OR%22%2C%22hlt%22%3A%22true%22%2C%22vlr%22%3A%22OR%22%2C%22val%22%3A%22%E5%8D%8E%E4%B8%AD%E7%90%86%E5%B7%A5%E5%A4%A7%E5%AD%A6%22%7D%2C%7B%22fld%22%3A%22subTitle%22%2C%22cdr%22%3A%22OR%22%2C%22hlt%22%3A%22true%22%2C%22vlr%22%3A%22OR%22%2C%22val%22%3A%22%E5%8D%8E%E4%B8%AD%E7%90%86%E5%B7%A5%E5%A4%A7%E5%AD%A6%22%7D%2C%7B%22fld%22%3A%22introTitle%22%2C%22cdr%22%3A%22OR%22%2C%22hlt%22%3A%22true%22%2C%22vlr%22%3A%22OR%22%2C%22val%22%3A%22%E5%8D%8E%E4%B8%AD%E7%90%86%E5%B7%A5%E5%A4%A7%E5%AD%A6%22%7D%5D%7D%5D%2C%22obs%22%3A%5B%7B%22fld%22%3A%22dataTime%22%2C%22drt%22%3A%22DESC%22%7D%5D%7D&tr=A&pageNo=1&pageSize=500&position=39", "source": "1999年9月20日第3版"},
{"title": "华中理工大学CIMS技术达国际先进水平", "url": "http://data.people.com.cn/rmrb/pd.html?qs=%7B%22cds%22%3A%5B%7B%22cdr%22%3A%22AND%22%2C%22cds%22%3A%5B%7B%22fld%22%3A%22title%22%2C%22cdr%22%3A%22OR%22%2C%22hlt%22%3A%22true%22%2C%22vlr%22%3A%22OR%22%2C%22val%22%3A%22%E5%8D%8E%E4%B8%AD%E7%90%86%E5%B7%A5%E5%A4%A7%E5%AD%A6%22%7D%2C%7B%22fld%22%3A%22subTitle%22%2C%22cdr%22%3A%22OR%22%2C%22hlt%22%3A%22true%22%2C%22vlr%22%3A%22OR%22%2C%22val%22%3A%22%E5%8D%8E%E4%B8%AD%E7%90%86%E5%B7%A5%E5%A4%A7%E5%AD%A6%22%7D%2C%7B%22fld%22%3A%22introTitle%22%2C%22cdr%22%3A%22OR%22%2C%22hlt%22%3A%22true%22%2C%22vlr%22%3A%22OR%22%2C%22val%22%3A%22%E5%8D%8E%E4%B8%AD%E7%90%86%E5%B7%A5%E5%A4%A7%E5%AD%A6%22%7D%5D%7D%5D%2C%22obs%22%3A%5B%7B%22fld%22%3A%22dataTime%22%2C%22drt%22%3A%22DESC%22%7D%5D%7D&tr=A&pageNo=1&pageSize=500&position=40", "source": "1999年9月20日第3版"},
{"title": "华中理工大学精官简政", "url": "http://data.people.com.cn/rmrb/pd.html?qs=%7B%22cds%22%3A%5B%7B%22cdr%22%3A%22AND%22%2C%22cds%22%3A%5B%7B%22fld%22%3A%22title%22%2C%22cdr%22%3A%22OR%22%2C%22hlt%22%3A%22true%22%2C%22vlr%22%3A%22OR%22%2C%22val%22%3A%22%E5%8D%8E%E4%B8%AD%E7%90%86%E5%B7%A5%E5%A4%A7%E5%AD%A6%22%7D%2C%7B%22fld%22%3A%22subTitle%22%2C%22cdr%22%3A%22OR%22%2C%22hlt%22%3A%22true%22%2C%22vlr%22%3A%22OR%22%2C%22val%22%3A%22%E5%8D%8E%E4%B8%AD%E7%90%86%E5%B7%A5%E5%A4%A7%E5%AD%A6%22%7D%2C%7B%22fld%22%3A%22introTitle%22%2C%22cdr%22%3A%22OR%22%2C%22hlt%22%3A%22true%22%2C%22vlr%22%3A%22OR%22%2C%22val%22%3A%22%E5%8D%8E%E4%B8%AD%E7%90%86%E5%B7%A5%E5%A4%A7%E5%AD%A6%22%7D%5D%7D%5D%2C%22obs%22%3A%5B%7B%22fld%22%3A%22dataTime%22%2C%22drt%22%3A%22DESC%22%7D%5D%7D&tr=A&pageNo=1&pageSize=500&position=45", "source": "1998年10月14日第5版"},
{"title": "周济出任华中理工大学校长", "url": "http://data.people.com.cn/rmrb/pd.html?qs=%7B%22cds%22%3A%5B%7B%22cdr%22%3A%22AND%22%2C%22cds%22%3A%5B%7B%22fld%22%3A%22title%22%2C%22cdr%22%3A%22OR%22%2C%22hlt%22%3A%22true%22%2C%22vlr%22%3A%22OR%22%2C%22val%22%3A%22%E5%8D%8E%E4%B8%AD%E7%90%86%E5%B7%A5%E5%A4%A7%E5%AD%A6%22%7D%2C%7B%22fld%22%3A%22subTitle%22%2C%22cdr%22%3A%22OR%22%2C%22hlt%22%3A%22true%22%2C%22vlr%22%3A%22OR%22%2C%22val%22%3A%22%E5%8D%8E%E4%B8%AD%E7%90%86%E5%B7%A5%E5%A4%A7%E5%AD%A6%22%7D%2C%7B%22fld%22%3A%22introTitle%22%2C%22cdr%22%3A%22OR%22%2C%22hlt%22%3A%22true%22%2C%22vlr%22%3A%22OR%22%2C%22val%22%3A%22%E5%8D%8E%E4%B8%AD%E7%90%86%E5%B7%A5%E5%A4%A7%E5%AD%A6%22%7D%5D%7D%5D%2C%22obs%22%3A%5B%7B%22fld%22%3A%22dataTime%22%2C%22drt%22%3A%22DESC%22%7D%5D%7D&tr=A&pageNo=1&pageSize=500&position=52", "source": "1997年11月12日第5版"},
{"title": "华中理工大学科研呈现新格局", "url": "http://data.people.com.cn/rmrb/pd.html?qs=%7B%22cds%22%3A%5B%7B%22cdr%22%3A%22AND%22%2C%22cds%22%3A%5B%7B%22fld%22%3A%22title%22%2C%22cdr%22%3A%22OR%22%2C%22hlt%22%3A%22true%22%2C%22vlr%22%3A%22OR%22%2C%22val%22%3A%22%E5%8D%8E%E4%B8%AD%E7%90%86%E5%B7%A5%E5%A4%A7%E5%AD%A6%22%7D%2C%7B%22fld%22%3A%22subTitle%22%2C%22cdr%22%3A%22OR%22%2C%22hlt%22%3A%22true%22%2C%22vlr%22%3A%22OR%22%2C%22val%22%3A%22%E5%8D%8E%E4%B8%AD%E7%90%86%E5%B7%A5%E5%A4%A7%E5%AD%A6%22%7D%2C%7B%22fld%22%3A%22introTitle%22%2C%22cdr%22%3A%22OR%22%2C%22hlt%22%3A%22true%22%2C%22vlr%22%3A%22OR%22%2C%22val%22%3A%22%E5%8D%8E%E4%B8%AD%E7%90%86%E5%B7%A5%E5%A4%A7%E5%AD%A6%22%7D%5D%7D%5D%2C%22obs%22%3A%5B%7B%22fld%22%3A%22dataTime%22%2C%22drt%22%3A%22DESC%22%7D%5D%7D&tr=A&pageNo=1&pageSize=500&position=57", "source": "1995年11月15日第5版"},
{"title": "人文精神与现代科技对话（——记华中理工大学的人文教育）", "url": "http://data.people.com.cn/rmrb/pd.html?qs=%7B%22cds%22%3A%5B%7B%22cdr%22%3A%22AND%22%2C%22cds%22%3A%5B%7B%22fld%22%3A%22title%22%2C%22cdr%22%3A%22OR%22%2C%22hlt%22%3A%22true%22%2C%22vlr%22%3A%22OR%22%2C%22val%22%3A%22%E5%8D%8E%E4%B8%AD%E7%90%86%E5%B7%A5%E5%A4%A7%E5%AD%A6%22%7D%2C%7B%22fld%22%3A%22subTitle%22%2C%22cdr%22%3A%22OR%22%2C%22hlt%22%3A%22true%22%2C%22vlr%22%3A%22OR%22%2C%22val%22%3A%22%E5%8D%8E%E4%B8%AD%E7%90%86%E5%B7%A5%E5%A4%A7%E5%AD%A6%22%7D%2C%7B%22fld%22%3A%22introTitle%22%2C%22cdr%22%3A%22OR%22%2C%22hlt%22%3A%22true%22%2C%22vlr%22%3A%22OR%22%2C%22val%22%3A%22%E5%8D%8E%E4%B8%AD%E7%90%86%E5%B7%A5%E5%A4%A7%E5%AD%A6%22%7D%5D%7D%5D%2C%22obs%22%3A%5B%7B%22fld%22%3A%22dataTime%22%2C%22drt%22%3A%22DESC%22%7D%5D%7D&tr=A&pageNo=1&pageSize=500&position=59", "source": "1995年9月18日第11版"},
{"title": "华中理工大学建校四十周年", "url": "http://data.people.com.cn/rmrb/pd.html?qs=%7B%22cds%22%3A%5B%7B%22cdr%22%3A%22AND%22%2C%22cds%22%3A%5B%7B%22fld%22%3A%22title%22%2C%22cdr%22%3A%22OR%22%2C%22hlt%22%3A%22true%22%2C%22vlr%22%3A%22OR%22%2C%22val%22%3A%22%E5%8D%8E%E4%B8%AD%E7%90%86%E5%B7%A5%E5%A4%A7%E5%AD%A6%22%7D%2C%7B%22fld%22%3A%22subTitle%22%2C%22cdr%22%3A%22OR%22%2C%22hlt%22%3A%22true%22%2C%22vlr%22%3A%22OR%22%2C%22val%22%3A%22%E5%8D%8E%E4%B8%AD%E7%90%86%E5%B7%A5%E5%A4%A7%E5%AD%A6%22%7D%2C%7B%22fld%22%3A%22introTitle%22%2C%22cdr%22%3A%22OR%22%2C%22hlt%22%3A%22true%22%2C%22vlr%22%3A%22OR%22%2C%22val%22%3A%22%E5%8D%8E%E4%B8%AD%E7%90%86%E5%B7%A5%E5%A4%A7%E5%AD%A6%22%7D%5D%7D%5D%2C%22obs%22%3A%5B%7B%22fld%22%3A%22dataTime%22%2C%22drt%22%3A%22DESC%22%7D%5D%7D&tr=A&pageNo=1&pageSize=500&position=65", "source": "1993年10月18日第3版"},
{"title": "华中理工大学医用激光造福人民", "url": "http://data.people.com.cn/rmrb/pd.html?qs=%7B%22cds%22%3A%5B%7B%22cdr%22%3A%22AND%22%2C%22cds%22%3A%5B%7B%22fld%22%3A%22title%22%2C%22cdr%22%3A%22OR%22%2C%22hlt%22%3A%22true%22%2C%22vlr%22%3A%22OR%22%2C%22val%22%3A%22%E5%8D%8E%E4%B8%AD%E7%90%86%E5%B7%A5%E5%A4%A7%E5%AD%A6%22%7D%2C%7B%22fld%22%3A%22subTitle%22%2C%22cdr%22%3A%22OR%22%2C%22hlt%22%3A%22true%22%2C%22vlr%22%3A%22OR%22%2C%22val%22%3A%22%E5%8D%8E%E4%B8%AD%E7%90%86%E5%B7%A5%E5%A4%A7%E5%AD%A6%22%7D%2C%7B%22fld%22%3A%22introTitle%22%2C%22cdr%22%3A%22OR%22%2C%22hlt%22%3A%22true%22%2C%22vlr%22%3A%22OR%22%2C%22val%22%3A%22%E5%8D%8E%E4%B8%AD%E7%90%86%E5%B7%A5%E5%A4%A7%E5%AD%A6%22%7D%5D%7D%5D%2C%22obs%22%3A%5B%7B%22fld%22%3A%22dataTime%22%2C%22drt%22%3A%22DESC%22%7D%5D%7D&tr=A&pageNo=1&pageSize=500&position=66", "source": "1993年7月14日第3版"},
{"title": "华中理工大学与企业合作 发挥自身优势推进技术进步", "url": "http://data.people.com.cn/rmrb/pd.html?qs=%7B%22cds%22%3A%5B%7B%22cdr%22%3A%22AND%22%2C%22cds%22%3A%5B%7B%22fld%22%3A%22title%22%2C%22cdr%22%3A%22OR%22%2C%22hlt%22%3A%22true%22%2C%22vlr%22%3A%22OR%22%2C%22val%22%3A%22%E5%8D%8E%E4%B8%AD%E7%90%86%E5%B7%A5%E5%A4%A7%E5%AD%A6%22%7D%2C%7B%22fld%22%3A%22subTitle%22%2C%22cdr%22%3A%22OR%22%2C%22hlt%22%3A%22true%22%2C%22vlr%22%3A%22OR%22%2C%22val%22%3A%22%E5%8D%8E%E4%B8%AD%E7%90%86%E5%B7%A5%E5%A4%A7%E5%AD%A6%22%7D%2C%7B%22fld%22%3A%22introTitle%22%2C%22cdr%22%3A%22OR%22%2C%22hlt%22%3A%22true%22%2C%22vlr%22%3A%22OR%22%2C%22val%22%3A%22%E5%8D%8E%E4%B8%AD%E7%90%86%E5%B7%A5%E5%A4%A7%E5%AD%A6%22%7D%5D%7D%5D%2C%22obs%22%3A%5B%7B%22fld%22%3A%22dataTime%22%2C%22drt%22%3A%22DESC%22%7D%5D%7D&tr=A&pageNo=1&pageSize=500&position=68", "source": "1992年1月15日第3版"},
{"title": "华中理工大学按系招生　入学二三年后再定专业", "url": "http://data.people.com.cn/rmrb/pd.html?qs=%7B%22cds%22%3A%5B%7B%22cdr%22%3A%22AND%22%2C%22cds%22%3A%5B%7B%22fld%22%3A%22title%22%2C%22cdr%22%3A%22OR%22%2C%22hlt%22%3A%22true%22%2C%22vlr%22%3A%22OR%22%2C%22val%22%3A%22%E5%8D%8E%E4%B8%AD%E7%90%86%E5%B7%A5%E5%A4%A7%E5%AD%A6%22%7D%2C%7B%22fld%22%3A%22subTitle%22%2C%22cdr%22%3A%22OR%22%2C%22hlt%22%3A%22true%22%2C%22vlr%22%3A%22OR%22%2C%22val%22%3A%22%E5%8D%8E%E4%B8%AD%E7%90%86%E5%B7%A5%E5%A4%A7%E5%AD%A6%22%7D%2C%7B%22fld%22%3A%22introTitle%22%2C%22cdr%22%3A%22OR%22%2C%22hlt%22%3A%22true%22%2C%22vlr%22%3A%22OR%22%2C%22val%22%3A%22%E5%8D%8E%E4%B8%AD%E7%90%86%E5%B7%A5%E5%A4%A7%E5%AD%A6%22%7D%5D%7D%5D%2C%22obs%22%3A%5B%7B%22fld%22%3A%22dataTime%22%2C%22drt%22%3A%22DESC%22%7D%5D%7D&tr=A&pageNo=1&pageSize=500&position=72", "source": "1988年5月23日第3版"},
{"title": "华中理工大学改进毕业生思想教育", "url": "http://data.people.com.cn/rmrb/pd.html?qs=%7B%22cds%22%3A%5B%7B%22cdr%22%3A%22AND%22%2C%22cds%22%3A%5B%7B%22fld%22%3A%22title%22%2C%22cdr%22%3A%22OR%22%2C%22hlt%22%3A%22true%22%2C%22vlr%22%3A%22OR%22%2C%22val%22%3A%22%E5%8D%8E%E4%B8%AD%E7%90%86%E5%B7%A5%E5%A4%A7%E5%AD%A6%22%7D%2C%7B%22fld%22%3A%22subTitle%22%2C%22cdr%22%3A%22OR%22%2C%22hlt%22%3A%22true%22%2C%22vlr%22%3A%22OR%22%2C%22val%22%3A%22%E5%8D%8E%E4%B8%AD%E7%90%86%E5%B7%A5%E5%A4%A7%E5%AD%A6%22%7D%2C%7B%22fld%22%3A%22introTitle%22%2C%22cdr%22%3A%22OR%22%2C%22hlt%22%3A%22true%22%2C%22vlr%22%3A%22OR%22%2C%22val%22%3A%22%E5%8D%8E%E4%B8%AD%E7%90%86%E5%B7%A5%E5%A4%A7%E5%AD%A6%22%7D%5D%7D%5D%2C%22obs%22%3A%5B%7B%22fld%22%3A%22dataTime%22%2C%22drt%22%3A%22DESC%22%7D%5D%7D&tr=A&pageNo=1&pageSize=500&position=75", "source": "1988年2月25日第3版"},
{"title": "工人大学生回厂后发挥很大作用　　从华中工学院毕业的一批工人大学生，在生产岗位上，运用在大学所学的理论知识解决生产实际问题，受到工厂领导和群众的赞扬", "url": "http://data.people.com.cn/rmrb/pd.html?qs=%7B%22cds%22%3A%5B%7B%22cdr%22%3A%22AND%22%2C%22cds%22%3A%5B%7B%22fld%22%3A%22title%22%2C%22cdr%22%3A%22OR%22%2C%22hlt%22%3A%22true%22%2C%22vlr%22%3A%22OR%22%2C%22val%22%3A%22%E5%8D%8E%E4%B8%AD%E7%90%86%E5%B7%A5%E5%A4%A7%E5%AD%A6%22%7D%2C%7B%22fld%22%3A%22subTitle%22%2C%22cdr%22%3A%22OR%22%2C%22hlt%22%3A%22true%22%2C%22vlr%22%3A%22OR%22%2C%22val%22%3A%22%E5%8D%8E%E4%B8%AD%E7%90%86%E5%B7%A5%E5%A4%A7%E5%AD%A6%22%7D%2C%7B%22fld%22%3A%22introTitle%22%2C%22cdr%22%3A%22OR%22%2C%22hlt%22%3A%22true%22%2C%22vlr%22%3A%22OR%22%2C%22val%22%3A%22%E5%8D%8E%E4%B8%AD%E7%90%86%E5%B7%A5%E5%A4%A7%E5%AD%A6%22%7D%5D%7D%5D%2C%22obs%22%3A%5B%7B%22fld%22%3A%22dataTime%22%2C%22drt%22%3A%22DESC%22%7D%5D%7D&tr=A&pageNo=1&pageSize=500&position=76", "source": "1973年3月19日第1版"},
{"title": "武汉重型机床厂和华中工学院等联合办学的果实　    业余大学首届毕业生成绩优良", "url": "http://data.people.com.cn/rmrb/pd.html?qs=%7B%22cds%22%3A%5B%7B%22cdr%22%3A%22AND%22%2C%22cds%22%3A%5B%7B%22fld%22%3A%22title%22%2C%22cdr%22%3A%22OR%22%2C%22hlt%22%3A%22true%22%2C%22vlr%22%3A%22OR%22%2C%22val%22%3A%22%E5%8D%8E%E4%B8%AD%E7%90%86%E5%B7%A5%E5%A4%A7%E5%AD%A6%22%7D%2C%7B%22fld%22%3A%22subTitle%22%2C%22cdr%22%3A%22OR%22%2C%22hlt%22%3A%22true%22%2C%22vlr%22%3A%22OR%22%2C%22val%22%3A%22%E5%8D%8E%E4%B8%AD%E7%90%86%E5%B7%A5%E5%A4%A7%E5%AD%A6%22%7D%2C%7B%22fld%22%3A%22introTitle%22%2C%22cdr%22%3A%22OR%22%2C%22hlt%22%3A%22true%22%2C%22vlr%22%3A%22OR%22%2C%22val%22%3A%22%E5%8D%8E%E4%B8%AD%E7%90%86%E5%B7%A5%E5%A4%A7%E5%AD%A6%22%7D%5D%7D%5D%2C%22obs%22%3A%5B%7B%22fld%22%3A%22dataTime%22%2C%22drt%22%3A%22DESC%22%7D%5D%7D&tr=A&pageNo=1&pageSize=500&position=77", "source": "1961年12月13日第4版"},
{"title": "潜心研究十余载，华中科技大学教授周敏康—— 更精微地感知重力（科技自立自强·青年科学家）", "url": "http://data.people.com.cn/rmrb/pd.html?qs=%7B%22cds%22%3A%5B%7B%22cdr%22%3A%22AND%22%2C%22cds%22%3A%5B%7B%22fld%22%3A%22title%22%2C%22cdr%22%3A%22OR%22%2C%22hlt%22%3A%22true%22%2C%22vlr%22%3A%22OR%22%2C%22val%22%3A%22%E5%8D%8E%E4%B8%AD%E7%A7%91%E6%8A%80%E5%A4%A7%E5%AD%A6%22%7D%2C%7B%22fld%22%3A%22subTitle%22%2C%22cdr%22%3A%22OR%22%2C%22hlt%22%3A%22true%22%2C%22vlr%22%3A%22OR%22%2C%22val%22%3A%22%E5%8D%8E%E4%B8%AD%E7%A7%91%E6%8A%80%E5%A4%A7%E5%AD%A6%22%7D%2C%7B%22fld%22%3A%22introTitle%22%2C%22cdr%22%3A%22OR%22%2C%22hlt%22%3A%22true%22%2C%22vlr%22%3A%22OR%22%2C%22val%22%3A%22%E5%8D%8E%E4%B8%AD%E7%A7%91%E6%8A%80%E5%A4%A7%E5%AD%A6%22%7D%5D%7D%5D%2C%22obs%22%3A%5B%7B%22fld%22%3A%22dataTime%22%2C%22drt%22%3A%22DESC%22%7D%5D%7D&tr=A&pageNo=1&pageSize=500&position=2", "source": "2022年4月14日第13版"},
{"title": "摘得国际EDA竞赛冠军，华中科技大学计算机学院90后团队—— 探前沿算法 解应用难题（科技自立自强·青年科学家）", "url": "http://data.people.com.cn/rmrb/pd.html?qs=%7B%22cds%22%3A%5B%7B%22cdr%22%3A%22AND%22%2C%22cds%22%3A%5B%7B%22fld%22%3A%22title%22%2C%22cdr%22%3A%22OR%22%2C%22hlt%22%3A%22true%22%2C%22vlr%22%3A%22OR%22%2C%22val%22%3A%22%E5%8D%8E%E4%B8%AD%E7%A7%91%E6%8A%80%E5%A4%A7%E5%AD%A6%22%7D%2C%7B%22fld%22%3A%22subTitle%22%2C%22cdr%22%3A%22OR%22%2C%22hlt%22%3A%22true%22%2C%22vlr%22%3A%22OR%22%2C%22val%22%3A%22%E5%8D%8E%E4%B8%AD%E7%A7%91%E6%8A%80%E5%A4%A7%E5%AD%A6%22%7D%2C%7B%22fld%22%3A%22introTitle%22%2C%22cdr%22%3A%22OR%22%2C%22hlt%22%3A%22true%22%2C%22vlr%22%3A%22OR%22%2C%22val%22%3A%22%E5%8D%8E%E4%B8%AD%E7%A7%91%E6%8A%80%E5%A4%A7%E5%AD%A6%22%7D%5D%7D%5D%2C%22obs%22%3A%5B%7B%22fld%22%3A%22dataTime%22%2C%22drt%22%3A%22DESC%22%7D%5D%7D&tr=A&pageNo=1&pageSize=500&position=4", "source": "2021年11月23日第12版"},
{"title": "从事柔性电子研究10余年，华中科技大学教授黄永安—— 开奇思妙想 找攻关方向（科技自立自强·青年科学家）", "url": "http://data.people.com.cn/rmrb/pd.html?qs=%7B%22cds%22%3A%5B%7B%22cdr%22%3A%22AND%22%2C%22cds%22%3A%5B%7B%22fld%22%3A%22title%22%2C%22cdr%22%3A%22OR%22%2C%22hlt%22%3A%22true%22%2C%22vlr%22%3A%22OR%22%2C%22val%22%3A%22%E5%8D%8E%E4%B8%AD%E7%A7%91%E6%8A%80%E5%A4%A7%E5%AD%A6%22%7D%2C%7B%22fld%22%3A%22subTitle%22%2C%22cdr%22%3A%22OR%22%2C%22hlt%22%3A%22true%22%2C%22vlr%22%3A%22OR%22%2C%22val%22%3A%22%E5%8D%8E%E4%B8%AD%E7%A7%91%E6%8A%80%E5%A4%A7%E5%AD%A6%22%7D%2C%7B%22fld%22%3A%22introTitle%22%2C%22cdr%22%3A%22OR%22%2C%22hlt%22%3A%22true%22%2C%22vlr%22%3A%22OR%22%2C%22val%22%3A%22%E5%8D%8E%E4%B8%AD%E7%A7%91%E6%8A%80%E5%A4%A7%E5%AD%A6%22%7D%5D%7D%5D%2C%22obs%22%3A%5B%7B%22fld%22%3A%22dataTime%22%2C%22drt%22%3A%22DESC%22%7D%5D%7D&tr=A&pageNo=1&pageSize=500&position=6", "source": "2021年7月8日第12版"},
{"title": "勇往直前 守护生命（一线抗疫群英谱）（——记华中科技大学同济医学院附属同济医院“尖刀连”）", "url": "http://data.people.com.cn/rmrb/pd.html?qs=%7B%22cds%22%3A%5B%7B%22cdr%22%3A%22AND%22%2C%22cds%22%3A%5B%7B%22fld%22%3A%22title%22%2C%22cdr%22%3A%22OR%22%2C%22hlt%22%3A%22true%22%2C%22vlr%22%3A%22OR%22%2C%22val%22%3A%22%E5%8D%8E%E4%B8%AD%E7%A7%91%E6%8A%80%E5%A4%A7%E5%AD%A6%22%7D%2C%7B%22fld%22%3A%22subTitle%22%2C%22cdr%22%3A%22OR%22%2C%22hlt%22%3A%22true%22%2C%22vlr%22%3A%22OR%22%2C%22val%22%3A%22%E5%8D%8E%E4%B8%AD%E7%A7%91%E6%8A%80%E5%A4%A7%E5%AD%A6%22%7D%2C%7B%22fld%22%3A%22introTitle%22%2C%22cdr%22%3A%22OR%22%2C%22hlt%22%3A%22true%22%2C%22vlr%22%3A%22OR%22%2C%22val%22%3A%22%E5%8D%8E%E4%B8%AD%E7%A7%91%E6%8A%80%E5%A4%A7%E5%AD%A6%22%7D%5D%7D%5D%2C%22obs%22%3A%5B%7B%22fld%22%3A%22dataTime%22%2C%22drt%22%3A%22DESC%22%7D%5D%7D&tr=A&pageNo=1&pageSize=500&position=8", "source": "2020年9月21日第6版"},
{"title": "国务院联防联控机制联络组赴华中科技大学 调研检查高校复学复课前防控工作", "url": "http://data.people.com.cn/rmrb/pd.html?qs=%7B%22cds%22%3A%5B%7B%22cdr%22%3A%22AND%22%2C%22cds%22%3A%5B%7B%22fld%22%3A%22title%22%2C%22cdr%22%3A%22OR%22%2C%22hlt%22%3A%22true%22%2C%22vlr%22%3A%22OR%22%2C%22val%22%3A%22%E5%8D%8E%E4%B8%AD%E7%A7%91%E6%8A%80%E5%A4%A7%E5%AD%A6%22%7D%2C%7B%22fld%22%3A%22subTitle%22%2C%22cdr%22%3A%22OR%22%2C%22hlt%22%3A%22true%22%2C%22vlr%22%3A%22OR%22%2C%22val%22%3A%22%E5%8D%8E%E4%B8%AD%E7%A7%91%E6%8A%80%E5%A4%A7%E5%AD%A6%22%7D%2C%7B%22fld%22%3A%22introTitle%22%2C%22cdr%22%3A%22OR%22%2C%22hlt%22%3A%22true%22%2C%22vlr%22%3A%22OR%22%2C%22val%22%3A%22%E5%8D%8E%E4%B8%AD%E7%A7%91%E6%8A%80%E5%A4%A7%E5%AD%A6%22%7D%5D%7D%5D%2C%22obs%22%3A%5B%7B%22fld%22%3A%22dataTime%22%2C%22drt%22%3A%22DESC%22%7D%5D%7D&tr=A&pageNo=1&pageSize=500&position=9", "source": "2020年6月5日第2版"},
{"title": "华中科技大学辅导员奚哲—— “不是生而英勇，只是选择无畏”", "url": "http://data.people.com.cn/rmrb/pd.html?qs=%7B%22cds%22%3A%5B%7B%22cdr%22%3A%22AND%22%2C%22cds%22%3A%5B%7B%22fld%22%3A%22title%22%2C%22cdr%22%3A%22OR%22%2C%22hlt%22%3A%22true%22%2C%22vlr%22%3A%22OR%22%2C%22val%22%3A%22%E5%8D%8E%E4%B8%AD%E7%A7%91%E6%8A%80%E5%A4%A7%E5%AD%A6%22%7D%2C%7B%22fld%22%3A%22subTitle%22%2C%22cdr%22%3A%22OR%22%2C%22hlt%22%3A%22true%22%2C%22vlr%22%3A%22OR%22%2C%22val%22%3A%22%E5%8D%8E%E4%B8%AD%E7%A7%91%E6%8A%80%E5%A4%A7%E5%AD%A6%22%7D%2C%7B%22fld%22%3A%22introTitle%22%2C%22cdr%22%3A%22OR%22%2C%22hlt%22%3A%22true%22%2C%22vlr%22%3A%22OR%22%2C%22val%22%3A%22%E5%8D%8E%E4%B8%AD%E7%A7%91%E6%8A%80%E5%A4%A7%E5%AD%A6%22%7D%5D%7D%5D%2C%22obs%22%3A%5B%7B%22fld%22%3A%22dataTime%22%2C%22drt%22%3A%22DESC%22%7D%5D%7D&tr=A&pageNo=1&pageSize=500&position=11", "source": "2020年5月12日第11版"},
{"title": "华中科技大学电气与电子工程学院院长文劲宇—— 把每个学生好好培养出来", "url": "http://data.people.com.cn/rmrb/pd.html?qs=%7B%22cds%22%3A%5B%7B%22cdr%22%3A%22AND%22%2C%22cds%22%3A%5B%7B%22fld%22%3A%22title%22%2C%22cdr%22%3A%22OR%22%2C%22hlt%22%3A%22true%22%2C%22vlr%22%3A%22OR%22%2C%22val%22%3A%22%E5%8D%8E%E4%B8%AD%E7%A7%91%E6%8A%80%E5%A4%A7%E5%AD%A6%22%7D%2C%7B%22fld%22%3A%22subTitle%22%2C%22cdr%22%3A%22OR%22%2C%22hlt%22%3A%22true%22%2C%22vlr%22%3A%22OR%22%2C%22val%22%3A%22%E5%8D%8E%E4%B8%AD%E7%A7%91%E6%8A%80%E5%A4%A7%E5%AD%A6%22%7D%2C%7B%22fld%22%3A%22introTitle%22%2C%22cdr%22%3A%22OR%22%2C%22hlt%22%3A%22true%22%2C%22vlr%22%3A%22OR%22%2C%22val%22%3A%22%E5%8D%8E%E4%B8%AD%E7%A7%91%E6%8A%80%E5%A4%A7%E5%AD%A6%22%7D%5D%7D%5D%2C%22obs%22%3A%5B%7B%22fld%22%3A%22dataTime%22%2C%22drt%22%3A%22DESC%22%7D%5D%7D&tr=A&pageNo=1&pageSize=500&position=16", "source": "2018年9月19日第12版"},
{"title": "丁烈云代表（华中科技大学校长）： 扎根中国大地办大学（热议·高质量发展）", "url": "http://data.people.com.cn/rmrb/pd.html?qs=%7B%22cds%22%3A%5B%7B%22cdr%22%3A%22AND%22%2C%22cds%22%3A%5B%7B%22fld%22%3A%22title%22%2C%22cdr%22%3A%22OR%22%2C%22hlt%22%3A%22true%22%2C%22vlr%22%3A%22OR%22%2C%22val%22%3A%22%E5%8D%8E%E4%B8%AD%E7%A7%91%E6%8A%80%E5%A4%A7%E5%AD%A6%22%7D%2C%7B%22fld%22%3A%22subTitle%22%2C%22cdr%22%3A%22OR%22%2C%22hlt%22%3A%22true%22%2C%22vlr%22%3A%22OR%22%2C%22val%22%3A%22%E5%8D%8E%E4%B8%AD%E7%A7%91%E6%8A%80%E5%A4%A7%E5%AD%A6%22%7D%2C%7B%22fld%22%3A%22introTitle%22%2C%22cdr%22%3A%22OR%22%2C%22hlt%22%3A%22true%22%2C%22vlr%22%3A%22OR%22%2C%22val%22%3A%22%E5%8D%8E%E4%B8%AD%E7%A7%91%E6%8A%80%E5%A4%A7%E5%AD%A6%22%7D%5D%7D%5D%2C%22obs%22%3A%5B%7B%22fld%22%3A%22dataTime%22%2C%22drt%22%3A%22DESC%22%7D%5D%7D&tr=A&pageNo=1&pageSize=500&position=21", "source": "2018年3月14日第14版"},
{"title": "华中科技大学师生春节回家调研乡风民俗，听老乡说困扰道心声—— 人情债 真想减下来（新春走基层 春节返乡记）", "url": "http://data.people.com.cn/rmrb/pd.html?qs=%7B%22cds%22%3A%5B%7B%22cdr%22%3A%22AND%22%2C%22cds%22%3A%5B%7B%22fld%22%3A%22title%22%2C%22cdr%22%3A%22OR%22%2C%22hlt%22%3A%22true%22%2C%22vlr%22%3A%22OR%22%2C%22val%22%3A%22%E5%8D%8E%E4%B8%AD%E7%A7%91%E6%8A%80%E5%A4%A7%E5%AD%A6%22%7D%2C%7B%22fld%22%3A%22subTitle%22%2C%22cdr%22%3A%22OR%22%2C%22hlt%22%3A%22true%22%2C%22vlr%22%3A%22OR%22%2C%22val%22%3A%22%E5%8D%8E%E4%B8%AD%E7%A7%91%E6%8A%80%E5%A4%A7%E5%AD%A6%22%7D%2C%7B%22fld%22%3A%22introTitle%22%2C%22cdr%22%3A%22OR%22%2C%22hlt%22%3A%22true%22%2C%22vlr%22%3A%22OR%22%2C%22val%22%3A%22%E5%8D%8E%E4%B8%AD%E7%A7%91%E6%8A%80%E5%A4%A7%E5%AD%A6%22%7D%5D%7D%5D%2C%22obs%22%3A%5B%7B%22fld%22%3A%22dataTime%22%2C%22drt%22%3A%22DESC%22%7D%5D%7D&tr=A&pageNo=1&pageSize=500&position=26", "source": "2017年2月3日第4版"},
{"title": "华中科技大学教授张海鸥破解世界性难题，并与空客公司进行技术合作 全球领先，3D打印飞机零件（治学者）", "url": "http://data.people.com.cn/rmrb/pd.html?qs=%7B%22cds%22%3A%5B%7B%22cdr%22%3A%22AND%22%2C%22cds%22%3A%5B%7B%22fld%22%3A%22title%22%2C%22cdr%22%3A%22OR%22%2C%22hlt%22%3A%22true%22%2C%22vlr%22%3A%22OR%22%2C%22val%22%3A%22%E5%8D%8E%E4%B8%AD%E7%A7%91%E6%8A%80%E5%A4%A7%E5%AD%A6%22%7D%2C%7B%22fld%22%3A%22subTitle%22%2C%22cdr%22%3A%22OR%22%2C%22hlt%22%3A%22true%22%2C%22vlr%22%3A%22OR%22%2C%22val%22%3A%22%E5%8D%8E%E4%B8%AD%E7%A7%91%E6%8A%80%E5%A4%A7%E5%AD%A6%22%7D%2C%7B%22fld%22%3A%22introTitle%22%2C%22cdr%22%3A%22OR%22%2C%22hlt%22%3A%22true%22%2C%22vlr%22%3A%22OR%22%2C%22val%22%3A%22%E5%8D%8E%E4%B8%AD%E7%A7%91%E6%8A%80%E5%A4%A7%E5%AD%A6%22%7D%5D%7D%5D%2C%22obs%22%3A%5B%7B%22fld%22%3A%22dataTime%22%2C%22drt%22%3A%22DESC%22%7D%5D%7D&tr=A&pageNo=1&pageSize=500&position=27", "source": "2017年1月18日第12版"},
{"title": "华中科技大学常务副校长罗俊院士三十年如一日在山洞搞科研 这里是“世界引力中心”（以先锋模范为镜）", "url": "http://data.people.com.cn/rmrb/pd.html?qs=%7B%22cds%22%3A%5B%7B%22cdr%22%3A%22AND%22%2C%22cds%22%3A%5B%7B%22fld%22%3A%22title%22%2C%22cdr%22%3A%22OR%22%2C%22hlt%22%3A%22true%22%2C%22vlr%22%3A%22OR%22%2C%22val%22%3A%22%E5%8D%8E%E4%B8%AD%E7%A7%91%E6%8A%80%E5%A4%A7%E5%AD%A6%22%7D%2C%7B%22fld%22%3A%22subTitle%22%2C%22cdr%22%3A%22OR%22%2C%22hlt%22%3A%22true%22%2C%22vlr%22%3A%22OR%22%2C%22val%22%3A%22%E5%8D%8E%E4%B8%AD%E7%A7%91%E6%8A%80%E5%A4%A7%E5%AD%A6%22%7D%2C%7B%22fld%22%3A%22introTitle%22%2C%22cdr%22%3A%22OR%22%2C%22hlt%22%3A%22true%22%2C%22vlr%22%3A%22OR%22%2C%22val%22%3A%22%E5%8D%8E%E4%B8%AD%E7%A7%91%E6%8A%80%E5%A4%A7%E5%AD%A6%22%7D%5D%7D%5D%2C%22obs%22%3A%5B%7B%22fld%22%3A%22dataTime%22%2C%22drt%22%3A%22DESC%22%7D%5D%7D&tr=A&pageNo=1&pageSize=500&position=35", "source": "2013年11月7日第6版"},
{"title": "华中科技大学文华学院探索个性化教育—— “潜能导师”助力成长（教改在基层）", "url": "http://data.people.com.cn/rmrb/pd.html?qs=%7B%22cds%22%3A%5B%7B%22cdr%22%3A%22AND%22%2C%22cds%22%3A%5B%7B%22fld%22%3A%22title%22%2C%22cdr%22%3A%22OR%22%2C%22hlt%22%3A%22true%22%2C%22vlr%22%3A%22OR%22%2C%22val%22%3A%22%E5%8D%8E%E4%B8%AD%E7%A7%91%E6%8A%80%E5%A4%A7%E5%AD%A6%22%7D%2C%7B%22fld%22%3A%22subTitle%22%2C%22cdr%22%3A%22OR%22%2C%22hlt%22%3A%22true%22%2C%22vlr%22%3A%22OR%22%2C%22val%22%3A%22%E5%8D%8E%E4%B8%AD%E7%A7%91%E6%8A%80%E5%A4%A7%E5%AD%A6%22%7D%2C%7B%22fld%22%3A%22introTitle%22%2C%22cdr%22%3A%22OR%22%2C%22hlt%22%3A%22true%22%2C%22vlr%22%3A%22OR%22%2C%22val%22%3A%22%E5%8D%8E%E4%B8%AD%E7%A7%91%E6%8A%80%E5%A4%A7%E5%AD%A6%22%7D%5D%7D%5D%2C%22obs%22%3A%5B%7B%22fld%22%3A%22dataTime%22%2C%22drt%22%3A%22DESC%22%7D%5D%7D&tr=A&pageNo=1&pageSize=500&position=40", "source": "2012年9月8日第7版"},
{"title": "铆足劲儿做科研（——走进华中科技大学）", "url": "http://data.people.com.cn/rmrb/pd.html?qs=%7B%22cds%22%3A%5B%7B%22cdr%22%3A%22AND%22%2C%22cds%22%3A%5B%7B%22fld%22%3A%22title%22%2C%22cdr%22%3A%22OR%22%2C%22hlt%22%3A%22true%22%2C%22vlr%22%3A%22OR%22%2C%22val%22%3A%22%E5%8D%8E%E4%B8%AD%E7%A7%91%E6%8A%80%E5%A4%A7%E5%AD%A6%22%7D%2C%7B%22fld%22%3A%22subTitle%22%2C%22cdr%22%3A%22OR%22%2C%22hlt%22%3A%22true%22%2C%22vlr%22%3A%22OR%22%2C%22val%22%3A%22%E5%8D%8E%E4%B8%AD%E7%A7%91%E6%8A%80%E5%A4%A7%E5%AD%A6%22%7D%2C%7B%22fld%22%3A%22introTitle%22%2C%22cdr%22%3A%22OR%22%2C%22hlt%22%3A%22true%22%2C%22vlr%22%3A%22OR%22%2C%22val%22%3A%22%E5%8D%8E%E4%B8%AD%E7%A7%91%E6%8A%80%E5%A4%A7%E5%AD%A6%22%7D%5D%7D%5D%2C%22obs%22%3A%5B%7B%22fld%22%3A%22dataTime%22%2C%22drt%22%3A%22DESC%22%7D%5D%7D&tr=A&pageNo=1&pageSize=500&position=41", "source": "2012年8月22日第10版"},
{"title": "华中科技大学制止一起假冒招生行为", "url": "http://data.people.com.cn/rmrb/pd.html?qs=%7B%22cds%22%3A%5B%7B%22cdr%22%3A%22AND%22%2C%22cds%22%3A%5B%7B%22fld%22%3A%22title%22%2C%22cdr%22%3A%22OR%22%2C%22hlt%22%3A%22true%22%2C%22vlr%22%3A%22OR%22%2C%22val%22%3A%22%E5%8D%8E%E4%B8%AD%E7%A7%91%E6%8A%80%E5%A4%A7%E5%AD%A6%22%7D%2C%7B%22fld%22%3A%22subTitle%22%2C%22cdr%22%3A%22OR%22%2C%22hlt%22%3A%22true%22%2C%22vlr%22%3A%22OR%22%2C%22val%22%3A%22%E5%8D%8E%E4%B8%AD%E7%A7%91%E6%8A%80%E5%A4%A7%E5%AD%A6%22%7D%2C%7B%22fld%22%3A%22introTitle%22%2C%22cdr%22%3A%22OR%22%2C%22hlt%22%3A%22true%22%2C%22vlr%22%3A%22OR%22%2C%22val%22%3A%22%E5%8D%8E%E4%B8%AD%E7%A7%91%E6%8A%80%E5%A4%A7%E5%AD%A6%22%7D%5D%7D%5D%2C%22obs%22%3A%5B%7B%22fld%22%3A%22dataTime%22%2C%22drt%22%3A%22DESC%22%7D%5D%7D&tr=A&pageNo=1&pageSize=500&position=42", "source": "2012年7月4日第8版"},
{"title": "华中科技大学文华学院引导学生走上创业路—— 李宇迪：创业从校园启航（创业教育案例）", "url": "http://data.people.com.cn/rmrb/pd.html?qs=%7B%22cds%22%3A%5B%7B%22cdr%22%3A%22AND%22%2C%22cds%22%3A%5B%7B%22fld%22%3A%22title%22%2C%22cdr%22%3A%22OR%22%2C%22hlt%22%3A%22true%22%2C%22vlr%22%3A%22OR%22%2C%22val%22%3A%22%E5%8D%8E%E4%B8%AD%E7%A7%91%E6%8A%80%E5%A4%A7%E5%AD%A6%22%7D%2C%7B%22fld%22%3A%22subTitle%22%2C%22cdr%22%3A%22OR%22%2C%22hlt%22%3A%22true%22%2C%22vlr%22%3A%22OR%22%2C%22val%22%3A%22%E5%8D%8E%E4%B8%AD%E7%A7%91%E6%8A%80%E5%A4%A7%E5%AD%A6%22%7D%2C%7B%22fld%22%3A%22introTitle%22%2C%22cdr%22%3A%22OR%22%2C%22hlt%22%3A%22true%22%2C%22vlr%22%3A%22OR%22%2C%22val%22%3A%22%E5%8D%8E%E4%B8%AD%E7%A7%91%E6%8A%80%E5%A4%A7%E5%AD%A6%22%7D%5D%7D%5D%2C%22obs%22%3A%5B%7B%22fld%22%3A%22dataTime%22%2C%22drt%22%3A%22DESC%22%7D%5D%7D&tr=A&pageNo=1&pageSize=500&position=44", "source": "2012年6月15日第18版"},
{"title": "华中科技大学60岁校庆走起“学术范”", "url": "http://data.people.com.cn/rmrb/pd.html?qs=%7B%22cds%22%3A%5B%7B%22cdr%22%3A%22AND%22%2C%22cds%22%3A%5B%7B%22fld%22%3A%22title%22%2C%22cdr%22%3A%22OR%22%2C%22hlt%22%3A%22true%22%2C%22vlr%22%3A%22OR%22%2C%22val%22%3A%22%E5%8D%8E%E4%B8%AD%E7%A7%91%E6%8A%80%E5%A4%A7%E5%AD%A6%22%7D%2C%7B%22fld%22%3A%22subTitle%22%2C%22cdr%22%3A%22OR%22%2C%22hlt%22%3A%22true%22%2C%22vlr%22%3A%22OR%22%2C%22val%22%3A%22%E5%8D%8E%E4%B8%AD%E7%A7%91%E6%8A%80%E5%A4%A7%E5%AD%A6%22%7D%2C%7B%22fld%22%3A%22introTitle%22%2C%22cdr%22%3A%22OR%22%2C%22hlt%22%3A%22true%22%2C%22vlr%22%3A%22OR%22%2C%22val%22%3A%22%E5%8D%8E%E4%B8%AD%E7%A7%91%E6%8A%80%E5%A4%A7%E5%AD%A6%22%7D%5D%7D%5D%2C%22obs%22%3A%5B%7B%22fld%22%3A%22dataTime%22%2C%22drt%22%3A%22DESC%22%7D%5D%7D&tr=A&pageNo=1&pageSize=500&position=47", "source": "2012年3月2日第12版"},
{"title": "华中科技大学 打造聚集人才的“强磁场”（高校青年教师队伍建设）", "url": "http://data.people.com.cn/rmrb/pd.html?qs=%7B%22cds%22%3A%5B%7B%22cdr%22%3A%22AND%22%2C%22cds%22%3A%5B%7B%22fld%22%3A%22title%22%2C%22cdr%22%3A%22OR%22%2C%22hlt%22%3A%22true%22%2C%22vlr%22%3A%22OR%22%2C%22val%22%3A%22%E5%8D%8E%E4%B8%AD%E7%A7%91%E6%8A%80%E5%A4%A7%E5%AD%A6%22%7D%2C%7B%22fld%22%3A%22subTitle%22%2C%22cdr%22%3A%22OR%22%2C%22hlt%22%3A%22true%22%2C%22vlr%22%3A%22OR%22%2C%22val%22%3A%22%E5%8D%8E%E4%B8%AD%E7%A7%91%E6%8A%80%E5%A4%A7%E5%AD%A6%22%7D%2C%7B%22fld%22%3A%22introTitle%22%2C%22cdr%22%3A%22OR%22%2C%22hlt%22%3A%22true%22%2C%22vlr%22%3A%22OR%22%2C%22val%22%3A%22%E5%8D%8E%E4%B8%AD%E7%A7%91%E6%8A%80%E5%A4%A7%E5%AD%A6%22%7D%5D%7D%5D%2C%22obs%22%3A%5B%7B%22fld%22%3A%22dataTime%22%2C%22drt%22%3A%22DESC%22%7D%5D%7D&tr=A&pageNo=1&pageSize=500&position=49", "source": "2012年1月18日第6版"},
{"title": "在华中科技大学毕业典礼上的16分钟致辞，被掌声打断30次。学生说：我们早就是他的“粉丝” “根叔”怎样当校长（人物）", "url": "http://data.people.com.cn/rmrb/pd.html?qs=%7B%22cds%22%3A%5B%7B%22cdr%22%3A%22AND%22%2C%22cds%22%3A%5B%7B%22fld%22%3A%22title%22%2C%22cdr%22%3A%22OR%22%2C%22hlt%22%3A%22true%22%2C%22vlr%22%3A%22OR%22%2C%22val%22%3A%22%E5%8D%8E%E4%B8%AD%E7%A7%91%E6%8A%80%E5%A4%A7%E5%AD%A6%22%7D%2C%7B%22fld%22%3A%22subTitle%22%2C%22cdr%22%3A%22OR%22%2C%22hlt%22%3A%22true%22%2C%22vlr%22%3A%22OR%22%2C%22val%22%3A%22%E5%8D%8E%E4%B8%AD%E7%A7%91%E6%8A%80%E5%A4%A7%E5%AD%A6%22%7D%2C%7B%22fld%22%3A%22introTitle%22%2C%22cdr%22%3A%22OR%22%2C%22hlt%22%3A%22true%22%2C%22vlr%22%3A%22OR%22%2C%22val%22%3A%22%E5%8D%8E%E4%B8%AD%E7%A7%91%E6%8A%80%E5%A4%A7%E5%AD%A6%22%7D%5D%7D%5D%2C%22obs%22%3A%5B%7B%22fld%22%3A%22dataTime%22%2C%22drt%22%3A%22DESC%22%7D%5D%7D&tr=A&pageNo=1&pageSize=500&position=55", "source": "2010年6月29日第11版"},
{"title": "华中科技大学创新教育激发活力", "url": "http://data.people.com.cn/rmrb/pd.html?qs=%7B%22cds%22%3A%5B%7B%22cdr%22%3A%22AND%22%2C%22cds%22%3A%5B%7B%22fld%22%3A%22title%22%2C%22cdr%22%3A%22OR%22%2C%22hlt%22%3A%22true%22%2C%22vlr%22%3A%22OR%22%2C%22val%22%3A%22%E5%8D%8E%E4%B8%AD%E7%A7%91%E6%8A%80%E5%A4%A7%E5%AD%A6%22%7D%2C%7B%22fld%22%3A%22subTitle%22%2C%22cdr%22%3A%22OR%22%2C%22hlt%22%3A%22true%22%2C%22vlr%22%3A%22OR%22%2C%22val%22%3A%22%E5%8D%8E%E4%B8%AD%E7%A7%91%E6%8A%80%E5%A4%A7%E5%AD%A6%22%7D%2C%7B%22fld%22%3A%22introTitle%22%2C%22cdr%22%3A%22OR%22%2C%22hlt%22%3A%22true%22%2C%22vlr%22%3A%22OR%22%2C%22val%22%3A%22%E5%8D%8E%E4%B8%AD%E7%A7%91%E6%8A%80%E5%A4%A7%E5%AD%A6%22%7D%5D%7D%5D%2C%22obs%22%3A%5B%7B%22fld%22%3A%22dataTime%22%2C%22drt%22%3A%22DESC%22%7D%5D%7D&tr=A&pageNo=1&pageSize=500&position=57", "source": "2010年5月23日第1版"},
{"title": "未来工程师“点”亮江城（——记华中科技大学刘玉教授和她的点（Dian）团队）", "url": "http://data.people.com.cn/rmrb/pd.html?qs=%7B%22cds%22%3A%5B%7B%22cdr%22%3A%22AND%22%2C%22cds%22%3A%5B%7B%22fld%22%3A%22title%22%2C%22cdr%22%3A%22OR%22%2C%22hlt%22%3A%22true%22%2C%22vlr%22%3A%22OR%22%2C%22val%22%3A%22%E5%8D%8E%E4%B8%AD%E7%A7%91%E6%8A%80%E5%A4%A7%E5%AD%A6%22%7D%2C%7B%22fld%22%3A%22subTitle%22%2C%22cdr%22%3A%22OR%22%2C%22hlt%22%3A%22true%22%2C%22vlr%22%3A%22OR%22%2C%22val%22%3A%22%E5%8D%8E%E4%B8%AD%E7%A7%91%E6%8A%80%E5%A4%A7%E5%AD%A6%22%7D%2C%7B%22fld%22%3A%22introTitle%22%2C%22cdr%22%3A%22OR%22%2C%22hlt%22%3A%22true%22%2C%22vlr%22%3A%22OR%22%2C%22val%22%3A%22%E5%8D%8E%E4%B8%AD%E7%A7%91%E6%8A%80%E5%A4%A7%E5%AD%A6%22%7D%5D%7D%5D%2C%22obs%22%3A%5B%7B%22fld%22%3A%22dataTime%22%2C%22drt%22%3A%22DESC%22%7D%5D%7D&tr=A&pageNo=1&pageSize=500&position=58", "source": "2010年4月2日第8版"},
{"title": "华中科技大学党委书记路钢代表： 推进教育经费筹措机制改革（发言席）", "url": "http://data.people.com.cn/rmrb/pd.html?qs=%7B%22cds%22%3A%5B%7B%22cdr%22%3A%22AND%22%2C%22cds%22%3A%5B%7B%22fld%22%3A%22title%22%2C%22cdr%22%3A%22OR%22%2C%22hlt%22%3A%22true%22%2C%22vlr%22%3A%22OR%22%2C%22val%22%3A%22%E5%8D%8E%E4%B8%AD%E7%A7%91%E6%8A%80%E5%A4%A7%E5%AD%A6%22%7D%2C%7B%22fld%22%3A%22subTitle%22%2C%22cdr%22%3A%22OR%22%2C%22hlt%22%3A%22true%22%2C%22vlr%22%3A%22OR%22%2C%22val%22%3A%22%E5%8D%8E%E4%B8%AD%E7%A7%91%E6%8A%80%E5%A4%A7%E5%AD%A6%22%7D%2C%7B%22fld%22%3A%22introTitle%22%2C%22cdr%22%3A%22OR%22%2C%22hlt%22%3A%22true%22%2C%22vlr%22%3A%22OR%22%2C%22val%22%3A%22%E5%8D%8E%E4%B8%AD%E7%A7%91%E6%8A%80%E5%A4%A7%E5%AD%A6%22%7D%5D%7D%5D%2C%22obs%22%3A%5B%7B%22fld%22%3A%22dataTime%22%2C%22drt%22%3A%22DESC%22%7D%5D%7D&tr=A&pageNo=1&pageSize=500&position=59", "source": "2010年3月11日第11版"},
{"title": "完善现代大学制度的宝贵机遇（专家视角）（——就学分制改革对话华中科技大学党委副书记欧阳康教授）", "url": "http://data.people.com.cn/rmrb/pd.html?qs=%7B%22cds%22%3A%5B%7B%22cdr%22%3A%22AND%22%2C%22cds%22%3A%5B%7B%22fld%22%3A%22title%22%2C%22cdr%22%3A%22OR%22%2C%22hlt%22%3A%22true%22%2C%22vlr%22%3A%22OR%22%2C%22val%22%3A%22%E5%8D%8E%E4%B8%AD%E7%A7%91%E6%8A%80%E5%A4%A7%E5%AD%A6%22%7D%2C%7B%22fld%22%3A%22subTitle%22%2C%22cdr%22%3A%22OR%22%2C%22hlt%22%3A%22true%22%2C%22vlr%22%3A%22OR%22%2C%22val%22%3A%22%E5%8D%8E%E4%B8%AD%E7%A7%91%E6%8A%80%E5%A4%A7%E5%AD%A6%22%7D%2C%7B%22fld%22%3A%22introTitle%22%2C%22cdr%22%3A%22OR%22%2C%22hlt%22%3A%22true%22%2C%22vlr%22%3A%22OR%22%2C%22val%22%3A%22%E5%8D%8E%E4%B8%AD%E7%A7%91%E6%8A%80%E5%A4%A7%E5%AD%A6%22%7D%5D%7D%5D%2C%22obs%22%3A%5B%7B%22fld%22%3A%22dataTime%22%2C%22drt%22%3A%22DESC%22%7D%5D%7D&tr=A&pageNo=1&pageSize=500&position=61", "source": "2010年2月26日第18版"},
{"title": "李长春在华中科技大学调研时强调 认真学习贯彻胡锦涛总书记重要讲话  不断开创大学生思想政治教育工作新局面", "url": "http://data.people.com.cn/rmrb/pd.html?qs=%7B%22cds%22%3A%5B%7B%22cdr%22%3A%22AND%22%2C%22cds%22%3A%5B%7B%22fld%22%3A%22title%22%2C%22cdr%22%3A%22OR%22%2C%22hlt%22%3A%22true%22%2C%22vlr%22%3A%22OR%22%2C%22val%22%3A%22%E5%8D%8E%E4%B8%AD%E7%A7%91%E6%8A%80%E5%A4%A7%E5%AD%A6%22%7D%2C%7B%22fld%22%3A%22subTitle%22%2C%22cdr%22%3A%22OR%22%2C%22hlt%22%3A%22true%22%2C%22vlr%22%3A%22OR%22%2C%22val%22%3A%22%E5%8D%8E%E4%B8%AD%E7%A7%91%E6%8A%80%E5%A4%A7%E5%AD%A6%22%7D%2C%7B%22fld%22%3A%22introTitle%22%2C%22cdr%22%3A%22OR%22%2C%22hlt%22%3A%22true%22%2C%22vlr%22%3A%22OR%22%2C%22val%22%3A%22%E5%8D%8E%E4%B8%AD%E7%A7%91%E6%8A%80%E5%A4%A7%E5%AD%A6%22%7D%5D%7D%5D%2C%22obs%22%3A%5B%7B%22fld%22%3A%22dataTime%22%2C%22drt%22%3A%22DESC%22%7D%5D%7D&tr=A&pageNo=1&pageSize=500&position=66", "source": "2007年9月7日第1版"},
{"title": "李长春在华中科技大学调研时强调 认真学习贯彻胡锦涛总书记重要讲话  不断开创大学生思想政治教育工作新局面", "url": "http://data.people.com.cn/rmrb/pd.html?qs=%7B%22cds%22%3A%5B%7B%22cdr%22%3A%22AND%22%2C%22cds%22%3A%5B%7B%22fld%22%3A%22title%22%2C%22cdr%22%3A%22OR%22%2C%22hlt%22%3A%22true%22%2C%22vlr%22%3A%22OR%22%2C%22val%22%3A%22%E5%8D%8E%E4%B8%AD%E7%A7%91%E6%8A%80%E5%A4%A7%E5%AD%A6%22%7D%2C%7B%22fld%22%3A%22subTitle%22%2C%22cdr%22%3A%22OR%22%2C%22hlt%22%3A%22true%22%2C%22vlr%22%3A%22OR%22%2C%22val%22%3A%22%E5%8D%8E%E4%B8%AD%E7%A7%91%E6%8A%80%E5%A4%A7%E5%AD%A6%22%7D%2C%7B%22fld%22%3A%22introTitle%22%2C%22cdr%22%3A%22OR%22%2C%22hlt%22%3A%22true%22%2C%22vlr%22%3A%22OR%22%2C%22val%22%3A%22%E5%8D%8E%E4%B8%AD%E7%A7%91%E6%8A%80%E5%A4%A7%E5%AD%A6%22%7D%5D%7D%5D%2C%22obs%22%3A%5B%7B%22fld%22%3A%22dataTime%22%2C%22drt%22%3A%22DESC%22%7D%5D%7D&tr=A&pageNo=1&pageSize=500&position=67", "source": "2007年9月7日第2版"},
{"title": "近日，华中科技大学同济医学院招募了20名特殊的“病人”——— “标准化病人”引发争议", "url": "http://data.people.com.cn/rmrb/pd.html?qs=%7B%22cds%22%3A%5B%7B%22cdr%22%3A%22AND%22%2C%22cds%22%3A%5B%7B%22fld%22%3A%22title%22%2C%22cdr%22%3A%22OR%22%2C%22hlt%22%3A%22true%22%2C%22vlr%22%3A%22OR%22%2C%22val%22%3A%22%E5%8D%8E%E4%B8%AD%E7%A7%91%E6%8A%80%E5%A4%A7%E5%AD%A6%22%7D%2C%7B%22fld%22%3A%22subTitle%22%2C%22cdr%22%3A%22OR%22%2C%22hlt%22%3A%22true%22%2C%22vlr%22%3A%22OR%22%2C%22val%22%3A%22%E5%8D%8E%E4%B8%AD%E7%A7%91%E6%8A%80%E5%A4%A7%E5%AD%A6%22%7D%2C%7B%22fld%22%3A%22introTitle%22%2C%22cdr%22%3A%22OR%22%2C%22hlt%22%3A%22true%22%2C%22vlr%22%3A%22OR%22%2C%22val%22%3A%22%E5%8D%8E%E4%B8%AD%E7%A7%91%E6%8A%80%E5%A4%A7%E5%AD%A6%22%7D%5D%7D%5D%2C%22obs%22%3A%5B%7B%22fld%22%3A%22dataTime%22%2C%22drt%22%3A%22DESC%22%7D%5D%7D&tr=A&pageNo=1&pageSize=500&position=75", "source": "2005年4月11日第5版"},
{"title": "创造网络德育新课堂（焦点）（——华中科技大学网络思想教育侧记）", "url": "http://data.people.com.cn/rmrb/pd.html?qs=%7B%22cds%22%3A%5B%7B%22cdr%22%3A%22AND%22%2C%22cds%22%3A%5B%7B%22fld%22%3A%22title%22%2C%22cdr%22%3A%22OR%22%2C%22hlt%22%3A%22true%22%2C%22vlr%22%3A%22OR%22%2C%22val%22%3A%22%E5%8D%8E%E4%B8%AD%E7%A7%91%E6%8A%80%E5%A4%A7%E5%AD%A6%22%7D%2C%7B%22fld%22%3A%22subTitle%22%2C%22cdr%22%3A%22OR%22%2C%22hlt%22%3A%22true%22%2C%22vlr%22%3A%22OR%22%2C%22val%22%3A%22%E5%8D%8E%E4%B8%AD%E7%A7%91%E6%8A%80%E5%A4%A7%E5%AD%A6%22%7D%2C%7B%22fld%22%3A%22introTitle%22%2C%22cdr%22%3A%22OR%22%2C%22hlt%22%3A%22true%22%2C%22vlr%22%3A%22OR%22%2C%22val%22%3A%22%E5%8D%8E%E4%B8%AD%E7%A7%91%E6%8A%80%E5%A4%A7%E5%AD%A6%22%7D%5D%7D%5D%2C%22obs%22%3A%5B%7B%22fld%22%3A%22dataTime%22%2C%22drt%22%3A%22DESC%22%7D%5D%7D&tr=A&pageNo=1&pageSize=500&position=76", "source": "2005年1月20日第13版"},
{"title": "华中科技大学教授龙元担心—— 汉正街退化为“无印的城市”", "url": "http://data.people.com.cn/rmrb/pd.html?qs=%7B%22cds%22%3A%5B%7B%22cdr%22%3A%22AND%22%2C%22cds%22%3A%5B%7B%22fld%22%3A%22title%22%2C%22cdr%22%3A%22OR%22%2C%22hlt%22%3A%22true%22%2C%22vlr%22%3A%22OR%22%2C%22val%22%3A%22%E5%8D%8E%E4%B8%AD%E7%A7%91%E6%8A%80%E5%A4%A7%E5%AD%A6%22%7D%2C%7B%22fld%22%3A%22subTitle%22%2C%22cdr%22%3A%22OR%22%2C%22hlt%22%3A%22true%22%2C%22vlr%22%3A%22OR%22%2C%22val%22%3A%22%E5%8D%8E%E4%B8%AD%E7%A7%91%E6%8A%80%E5%A4%A7%E5%AD%A6%22%7D%2C%7B%22fld%22%3A%22introTitle%22%2C%22cdr%22%3A%22OR%22%2C%22hlt%22%3A%22true%22%2C%22vlr%22%3A%22OR%22%2C%22val%22%3A%22%E5%8D%8E%E4%B8%AD%E7%A7%91%E6%8A%80%E5%A4%A7%E5%AD%A6%22%7D%5D%7D%5D%2C%22obs%22%3A%5B%7B%22fld%22%3A%22dataTime%22%2C%22drt%22%3A%22DESC%22%7D%5D%7D&tr=A&pageNo=1&pageSize=500&position=78", "source": "2004年11月24日第5版"},
{"title": "随着经济全球化和我国加入WTO，中药产业国际化浪潮势不可挡。从人力资源角度讲，如何推动这一国际化进程？华中科技大学公共管理学院副教授徐顽强接受记者采访时，指出实现该目标的一个核心工作应是—— 以国外本土化带动中药国际化（本期关注——聚焦中医药（三））", "url": "http://data.people.com.cn/rmrb/pd.html?qs=%7B%22cds%22%3A%5B%7B%22cdr%22%3A%22AND%22%2C%22cds%22%3A%5B%7B%22fld%22%3A%22title%22%2C%22cdr%22%3A%22OR%22%2C%22hlt%22%3A%22true%22%2C%22vlr%22%3A%22OR%22%2C%22val%22%3A%22%E5%8D%8E%E4%B8%AD%E7%A7%91%E6%8A%80%E5%A4%A7%E5%AD%A6%22%7D%2C%7B%22fld%22%3A%22subTitle%22%2C%22cdr%22%3A%22OR%22%2C%22hlt%22%3A%22true%22%2C%22vlr%22%3A%22OR%22%2C%22val%22%3A%22%E5%8D%8E%E4%B8%AD%E7%A7%91%E6%8A%80%E5%A4%A7%E5%AD%A6%22%7D%2C%7B%22fld%22%3A%22introTitle%22%2C%22cdr%22%3A%22OR%22%2C%22hlt%22%3A%22true%22%2C%22vlr%22%3A%22OR%22%2C%22val%22%3A%22%E5%8D%8E%E4%B8%AD%E7%A7%91%E6%8A%80%E5%A4%A7%E5%AD%A6%22%7D%5D%7D%5D%2C%22obs%22%3A%5B%7B%22fld%22%3A%22dataTime%22%2C%22drt%22%3A%22DESC%22%7D%5D%7D&tr=A&pageNo=1&pageSize=500&position=79", "source": "2004年11月18日第15版"},
{"title": "让中国古老的《道德经》走进科学的殿堂，成为大学生的选修课，这是华中科技大学坚守“科学与人文结合”的具体体现，也为我国高校加强和改进思想道德教育提供了宝贵经验。请看本报记者的最新报道—— 人文之光照耀科学摇篮（焦点）（——华中科技大学用优秀传统文化提高学生思想道德素质纪事）", "url": "http://data.people.com.cn/rmrb/pd.html?qs=%7B%22cds%22%3A%5B%7B%22cdr%22%3A%22AND%22%2C%22cds%22%3A%5B%7B%22fld%22%3A%22title%22%2C%22cdr%22%3A%22OR%22%2C%22hlt%22%3A%22true%22%2C%22vlr%22%3A%22OR%22%2C%22val%22%3A%22%E5%8D%8E%E4%B8%AD%E7%A7%91%E6%8A%80%E5%A4%A7%E5%AD%A6%22%7D%2C%7B%22fld%22%3A%22subTitle%22%2C%22cdr%22%3A%22OR%22%2C%22hlt%22%3A%22true%22%2C%22vlr%22%3A%22OR%22%2C%22val%22%3A%22%E5%8D%8E%E4%B8%AD%E7%A7%91%E6%8A%80%E5%A4%A7%E5%AD%A6%22%7D%2C%7B%22fld%22%3A%22introTitle%22%2C%22cdr%22%3A%22OR%22%2C%22hlt%22%3A%22true%22%2C%22vlr%22%3A%22OR%22%2C%22val%22%3A%22%E5%8D%8E%E4%B8%AD%E7%A7%91%E6%8A%80%E5%A4%A7%E5%AD%A6%22%7D%5D%7D%5D%2C%22obs%22%3A%5B%7B%22fld%22%3A%22dataTime%22%2C%22drt%22%3A%22DESC%22%7D%5D%7D&tr=A&pageNo=1&pageSize=500&position=81", "source": "2004年5月13日第13版"},
{"title": "华中科技大学400多名学生寒假完成的一项特殊“家庭作业”，正引起绵绵不绝的回响 “我给爸妈洗洗脚”", "url": "http://data.people.com.cn/rmrb/pd.html?qs=%7B%22cds%22%3A%5B%7B%22cdr%22%3A%22AND%22%2C%22cds%22%3A%5B%7B%22fld%22%3A%22title%22%2C%22cdr%22%3A%22OR%22%2C%22hlt%22%3A%22true%22%2C%22vlr%22%3A%22OR%22%2C%22val%22%3A%22%E5%8D%8E%E4%B8%AD%E7%A7%91%E6%8A%80%E5%A4%A7%E5%AD%A6%22%7D%2C%7B%22fld%22%3A%22subTitle%22%2C%22cdr%22%3A%22OR%22%2C%22hlt%22%3A%22true%22%2C%22vlr%22%3A%22OR%22%2C%22val%22%3A%22%E5%8D%8E%E4%B8%AD%E7%A7%91%E6%8A%80%E5%A4%A7%E5%AD%A6%22%7D%2C%7B%22fld%22%3A%22introTitle%22%2C%22cdr%22%3A%22OR%22%2C%22hlt%22%3A%22true%22%2C%22vlr%22%3A%22OR%22%2C%22val%22%3A%22%E5%8D%8E%E4%B8%AD%E7%A7%91%E6%8A%80%E5%A4%A7%E5%AD%A6%22%7D%5D%7D%5D%2C%22obs%22%3A%5B%7B%22fld%22%3A%22dataTime%22%2C%22drt%22%3A%22DESC%22%7D%5D%7D&tr=A&pageNo=1&pageSize=500&position=82", "source": "2004年3月22日第5版"},
{"title": "华中科技大学　党支部建在班上", "url": "http://data.people.com.cn/rmrb/pd.html?qs=%7B%22cds%22%3A%5B%7B%22cdr%22%3A%22AND%22%2C%22cds%22%3A%5B%7B%22fld%22%3A%22title%22%2C%22cdr%22%3A%22OR%22%2C%22hlt%22%3A%22true%22%2C%22vlr%22%3A%22OR%22%2C%22val%22%3A%22%E5%8D%8E%E4%B8%AD%E7%A7%91%E6%8A%80%E5%A4%A7%E5%AD%A6%22%7D%2C%7B%22fld%22%3A%22subTitle%22%2C%22cdr%22%3A%22OR%22%2C%22hlt%22%3A%22true%22%2C%22vlr%22%3A%22OR%22%2C%22val%22%3A%22%E5%8D%8E%E4%B8%AD%E7%A7%91%E6%8A%80%E5%A4%A7%E5%AD%A6%22%7D%2C%7B%22fld%22%3A%22introTitle%22%2C%22cdr%22%3A%22OR%22%2C%22hlt%22%3A%22true%22%2C%22vlr%22%3A%22OR%22%2C%22val%22%3A%22%E5%8D%8E%E4%B8%AD%E7%A7%91%E6%8A%80%E5%A4%A7%E5%AD%A6%22%7D%5D%7D%5D%2C%22obs%22%3A%5B%7B%22fld%22%3A%22dataTime%22%2C%22drt%22%3A%22DESC%22%7D%5D%7D&tr=A&pageNo=1&pageSize=500&position=85", "source": "2003年10月28日第11版"},
{"title": "华中科技大学庆祝建校50周年", "url": "http://data.people.com.cn/rmrb/pd.html?qs=%7B%22cds%22%3A%5B%7B%22cdr%22%3A%22AND%22%2C%22cds%22%3A%5B%7B%22fld%22%3A%22title%22%2C%22cdr%22%3A%22OR%22%2C%22hlt%22%3A%22true%22%2C%22vlr%22%3A%22OR%22%2C%22val%22%3A%22%E5%8D%8E%E4%B8%AD%E7%A7%91%E6%8A%80%E5%A4%A7%E5%AD%A6%22%7D%2C%7B%22fld%22%3A%22subTitle%22%2C%22cdr%22%3A%22OR%22%2C%22hlt%22%3A%22true%22%2C%22vlr%22%3A%22OR%22%2C%22val%22%3A%22%E5%8D%8E%E4%B8%AD%E7%A7%91%E6%8A%80%E5%A4%A7%E5%AD%A6%22%7D%2C%7B%22fld%22%3A%22introTitle%22%2C%22cdr%22%3A%22OR%22%2C%22hlt%22%3A%22true%22%2C%22vlr%22%3A%22OR%22%2C%22val%22%3A%22%E5%8D%8E%E4%B8%AD%E7%A7%91%E6%8A%80%E5%A4%A7%E5%AD%A6%22%7D%5D%7D%5D%2C%22obs%22%3A%5B%7B%22fld%22%3A%22dataTime%22%2C%22drt%22%3A%22DESC%22%7D%5D%7D&tr=A&pageNo=1&pageSize=500&position=89", "source": "2003年10月9日第11版"},
{"title": "在共和国旗帜下成长（发展特色　争创优势）（———华中科技大学努力向国际化、研究型、综合性大学目标迈进）", "url": "http://data.people.com.cn/rmrb/pd.html?qs=%7B%22cds%22%3A%5B%7B%22cdr%22%3A%22AND%22%2C%22cds%22%3A%5B%7B%22fld%22%3A%22title%22%2C%22cdr%22%3A%22OR%22%2C%22hlt%22%3A%22true%22%2C%22vlr%22%3A%22OR%22%2C%22val%22%3A%22%E5%8D%8E%E4%B8%AD%E7%A7%91%E6%8A%80%E5%A4%A7%E5%AD%A6%22%7D%2C%7B%22fld%22%3A%22subTitle%22%2C%22cdr%22%3A%22OR%22%2C%22hlt%22%3A%22true%22%2C%22vlr%22%3A%22OR%22%2C%22val%22%3A%22%E5%8D%8E%E4%B8%AD%E7%A7%91%E6%8A%80%E5%A4%A7%E5%AD%A6%22%7D%2C%7B%22fld%22%3A%22introTitle%22%2C%22cdr%22%3A%22OR%22%2C%22hlt%22%3A%22true%22%2C%22vlr%22%3A%22OR%22%2C%22val%22%3A%22%E5%8D%8E%E4%B8%AD%E7%A7%91%E6%8A%80%E5%A4%A7%E5%AD%A6%22%7D%5D%7D%5D%2C%22obs%22%3A%5B%7B%22fld%22%3A%22dataTime%22%2C%22drt%22%3A%22DESC%22%7D%5D%7D&tr=A&pageNo=1&pageSize=500&position=90", "source": "2003年9月28日第8版"},
{"title": "后勤先行（──华中科技大学后勤社会化改革纪实）", "url": "http://data.people.com.cn/rmrb/pd.html?qs=%7B%22cds%22%3A%5B%7B%22cdr%22%3A%22AND%22%2C%22cds%22%3A%5B%7B%22fld%22%3A%22title%22%2C%22cdr%22%3A%22OR%22%2C%22hlt%22%3A%22true%22%2C%22vlr%22%3A%22OR%22%2C%22val%22%3A%22%E5%8D%8E%E4%B8%AD%E7%A7%91%E6%8A%80%E5%A4%A7%E5%AD%A6%22%7D%2C%7B%22fld%22%3A%22subTitle%22%2C%22cdr%22%3A%22OR%22%2C%22hlt%22%3A%22true%22%2C%22vlr%22%3A%22OR%22%2C%22val%22%3A%22%E5%8D%8E%E4%B8%AD%E7%A7%91%E6%8A%80%E5%A4%A7%E5%AD%A6%22%7D%2C%7B%22fld%22%3A%22introTitle%22%2C%22cdr%22%3A%22OR%22%2C%22hlt%22%3A%22true%22%2C%22vlr%22%3A%22OR%22%2C%22val%22%3A%22%E5%8D%8E%E4%B8%AD%E7%A7%91%E6%8A%80%E5%A4%A7%E5%AD%A6%22%7D%5D%7D%5D%2C%22obs%22%3A%5B%7B%22fld%22%3A%22dataTime%22%2C%22drt%22%3A%22DESC%22%7D%5D%7D&tr=A&pageNo=1&pageSize=500&position=100", "source": "2001年1月4日第6版"},
{"title": "武汉九所高校实行合并（组建华中科技大学、中南财经政法大学和武汉理工大学）", "url": "http://data.people.com.cn/rmrb/pd.html?qs=%7B%22cds%22%3A%5B%7B%22cdr%22%3A%22AND%22%2C%22cds%22%3A%5B%7B%22fld%22%3A%22title%22%2C%22cdr%22%3A%22OR%22%2C%22hlt%22%3A%22true%22%2C%22vlr%22%3A%22OR%22%2C%22val%22%3A%22%E5%8D%8E%E4%B8%AD%E7%A7%91%E6%8A%80%E5%A4%A7%E5%AD%A6%22%7D%2C%7B%22fld%22%3A%22subTitle%22%2C%22cdr%22%3A%22OR%22%2C%22hlt%22%3A%22true%22%2C%22vlr%22%3A%22OR%22%2C%22val%22%3A%22%E5%8D%8E%E4%B8%AD%E7%A7%91%E6%8A%80%E5%A4%A7%E5%AD%A6%22%7D%2C%7B%22fld%22%3A%22introTitle%22%2C%22cdr%22%3A%22OR%22%2C%22hlt%22%3A%22true%22%2C%22vlr%22%3A%22OR%22%2C%22val%22%3A%22%E5%8D%8E%E4%B8%AD%E7%A7%91%E6%8A%80%E5%A4%A7%E5%AD%A6%22%7D%5D%7D%5D%2C%22obs%22%3A%5B%7B%22fld%22%3A%22dataTime%22%2C%22drt%22%3A%22DESC%22%7D%5D%7D&tr=A&pageNo=1&pageSize=500&position=104", "source": "2000年5月29日第5版"},
{"title": "华中理工大学CIMS技术达国际先进水平", "url": "http://data.people.com.cn/rmrb/pd.html?qs=%7B%22cds%22%3A%5B%7B%22cdr%22%3A%22AND%22%2C%22cds%22%3A%5B%7B%22fld%22%3A%22title%22%2C%22cdr%22%3A%22OR%22%2C%22hlt%22%3A%22true%22%2C%22vlr%22%3A%22OR%22%2C%22val%22%3A%22%E5%8D%8E%E4%B8%AD%E7%A7%91%E6%8A%80%E5%A4%A7%E5%AD%A6%22%7D%2C%7B%22fld%22%3A%22subTitle%22%2C%22cdr%22%3A%22OR%22%2C%22hlt%22%3A%22true%22%2C%22vlr%22%3A%22OR%22%2C%22val%22%3A%22%E5%8D%8E%E4%B8%AD%E7%A7%91%E6%8A%80%E5%A4%A7%E5%AD%A6%22%7D%2C%7B%22fld%22%3A%22introTitle%22%2C%22cdr%22%3A%22OR%22%2C%22hlt%22%3A%22true%22%2C%22vlr%22%3A%22OR%22%2C%22val%22%3A%22%E5%8D%8E%E4%B8%AD%E7%A7%91%E6%8A%80%E5%A4%A7%E5%AD%A6%22%7D%5D%7D%5D%2C%22obs%22%3A%5B%7B%22fld%22%3A%22dataTime%22%2C%22drt%22%3A%22DESC%22%7D%5D%7D&tr=A&pageNo=1&pageSize=500&position=111", "source": "1999年9月20日第3版"},
{"title": "华中理工大学精官简政", "url": "http://data.people.com.cn/rmrb/pd.html?qs=%7B%22cds%22%3A%5B%7B%22cdr%22%3A%22AND%22%2C%22cds%22%3A%5B%7B%22fld%22%3A%22title%22%2C%22cdr%22%3A%22OR%22%2C%22hlt%22%3A%22true%22%2C%22vlr%22%3A%22OR%22%2C%22val%22%3A%22%E5%8D%8E%E4%B8%AD%E7%A7%91%E6%8A%80%E5%A4%A7%E5%AD%A6%22%7D%2C%7B%22fld%22%3A%22subTitle%22%2C%22cdr%22%3A%22OR%22%2C%22hlt%22%3A%22true%22%2C%22vlr%22%3A%22OR%22%2C%22val%22%3A%22%E5%8D%8E%E4%B8%AD%E7%A7%91%E6%8A%80%E5%A4%A7%E5%AD%A6%22%7D%2C%7B%22fld%22%3A%22introTitle%22%2C%22cdr%22%3A%22OR%22%2C%22hlt%22%3A%22true%22%2C%22vlr%22%3A%22OR%22%2C%22val%22%3A%22%E5%8D%8E%E4%B8%AD%E7%A7%91%E6%8A%80%E5%A4%A7%E5%AD%A6%22%7D%5D%7D%5D%2C%22obs%22%3A%5B%7B%22fld%22%3A%22dataTime%22%2C%22drt%22%3A%22DESC%22%7D%5D%7D&tr=A&pageNo=1&pageSize=500&position=114", "source": "1998年10月14日第5版"},
{"title": "周济出任华中理工大学校长", "url": "http://data.people.com.cn/rmrb/pd.html?qs=%7B%22cds%22%3A%5B%7B%22cdr%22%3A%22AND%22%2C%22cds%22%3A%5B%7B%22fld%22%3A%22title%22%2C%22cdr%22%3A%22OR%22%2C%22hlt%22%3A%22true%22%2C%22vlr%22%3A%22OR%22%2C%22val%22%3A%22%E5%8D%8E%E4%B8%AD%E7%A7%91%E6%8A%80%E5%A4%A7%E5%AD%A6%22%7D%2C%7B%22fld%22%3A%22subTitle%22%2C%22cdr%22%3A%22OR%22%2C%22hlt%22%3A%22true%22%2C%22vlr%22%3A%22OR%22%2C%22val%22%3A%22%E5%8D%8E%E4%B8%AD%E7%A7%91%E6%8A%80%E5%A4%A7%E5%AD%A6%22%7D%2C%7B%22fld%22%3A%22introTitle%22%2C%22cdr%22%3A%22OR%22%2C%22hlt%22%3A%22true%22%2C%22vlr%22%3A%22OR%22%2C%22val%22%3A%22%E5%8D%8E%E4%B8%AD%E7%A7%91%E6%8A%80%E5%A4%A7%E5%AD%A6%22%7D%5D%7D%5D%2C%22obs%22%3A%5B%7B%22fld%22%3A%22dataTime%22%2C%22drt%22%3A%22DESC%22%7D%5D%7D&tr=A&pageNo=1&pageSize=500&position=118", "source": "1997年11月12日第5版"},
{"title": "华中理工大学科研呈现新格局", "url": "http://data.people.com.cn/rmrb/pd.html?qs=%7B%22cds%22%3A%5B%7B%22cdr%22%3A%22AND%22%2C%22cds%22%3A%5B%7B%22fld%22%3A%22title%22%2C%22cdr%22%3A%22OR%22%2C%22hlt%22%3A%22true%22%2C%22vlr%22%3A%22OR%22%2C%22val%22%3A%22%E5%8D%8E%E4%B8%AD%E7%A7%91%E6%8A%80%E5%A4%A7%E5%AD%A6%22%7D%2C%7B%22fld%22%3A%22subTitle%22%2C%22cdr%22%3A%22OR%22%2C%22hlt%22%3A%22true%22%2C%22vlr%22%3A%22OR%22%2C%22val%22%3A%22%E5%8D%8E%E4%B8%AD%E7%A7%91%E6%8A%80%E5%A4%A7%E5%AD%A6%22%7D%2C%7B%22fld%22%3A%22introTitle%22%2C%22cdr%22%3A%22OR%22%2C%22hlt%22%3A%22true%22%2C%22vlr%22%3A%22OR%22%2C%22val%22%3A%22%E5%8D%8E%E4%B8%AD%E7%A7%91%E6%8A%80%E5%A4%A7%E5%AD%A6%22%7D%5D%7D%5D%2C%22obs%22%3A%5B%7B%22fld%22%3A%22dataTime%22%2C%22drt%22%3A%22DESC%22%7D%5D%7D&tr=A&pageNo=1&pageSize=500&position=124", "source": "1995年11月15日第5版"},
{"title": "华中理工大学建校四十周年", "url": "http://data.people.com.cn/rmrb/pd.html?qs=%7B%22cds%22%3A%5B%7B%22cdr%22%3A%22AND%22%2C%22cds%22%3A%5B%7B%22fld%22%3A%22title%22%2C%22cdr%22%3A%22OR%22%2C%22hlt%22%3A%22true%22%2C%22vlr%22%3A%22OR%22%2C%22val%22%3A%22%E5%8D%8E%E4%B8%AD%E7%A7%91%E6%8A%80%E5%A4%A7%E5%AD%A6%22%7D%2C%7B%22fld%22%3A%22subTitle%22%2C%22cdr%22%3A%22OR%22%2C%22hlt%22%3A%22true%22%2C%22vlr%22%3A%22OR%22%2C%22val%22%3A%22%E5%8D%8E%E4%B8%AD%E7%A7%91%E6%8A%80%E5%A4%A7%E5%AD%A6%22%7D%2C%7B%22fld%22%3A%22introTitle%22%2C%22cdr%22%3A%22OR%22%2C%22hlt%22%3A%22true%22%2C%22vlr%22%3A%22OR%22%2C%22val%22%3A%22%E5%8D%8E%E4%B8%AD%E7%A7%91%E6%8A%80%E5%A4%A7%E5%AD%A6%22%7D%5D%7D%5D%2C%22obs%22%3A%5B%7B%22fld%22%3A%22dataTime%22%2C%22drt%22%3A%22DESC%22%7D%5D%7D&tr=A&pageNo=1&pageSize=500&position=127", "source": "1993年10月18日第3版"},
{"title": "华中理工大学医用激光造福人民", "url": "http://data.people.com.cn/rmrb/pd.html?qs=%7B%22cds%22%3A%5B%7B%22cdr%22%3A%22AND%22%2C%22cds%22%3A%5B%7B%22fld%22%3A%22title%22%2C%22cdr%22%3A%22OR%22%2C%22hlt%22%3A%22true%22%2C%22vlr%22%3A%22OR%22%2C%22val%22%3A%22%E5%8D%8E%E4%B8%AD%E7%A7%91%E6%8A%80%E5%A4%A7%E5%AD%A6%22%7D%2C%7B%22fld%22%3A%22subTitle%22%2C%22cdr%22%3A%22OR%22%2C%22hlt%22%3A%22true%22%2C%22vlr%22%3A%22OR%22%2C%22val%22%3A%22%E5%8D%8E%E4%B8%AD%E7%A7%91%E6%8A%80%E5%A4%A7%E5%AD%A6%22%7D%2C%7B%22fld%22%3A%22introTitle%22%2C%22cdr%22%3A%22OR%22%2C%22hlt%22%3A%22true%22%2C%22vlr%22%3A%22OR%22%2C%22val%22%3A%22%E5%8D%8E%E4%B8%AD%E7%A7%91%E6%8A%80%E5%A4%A7%E5%AD%A6%22%7D%5D%7D%5D%2C%22obs%22%3A%5B%7B%22fld%22%3A%22dataTime%22%2C%22drt%22%3A%22DESC%22%7D%5D%7D&tr=A&pageNo=1&pageSize=500&position=129", "source": "1993年7月14日第3版"},
{"title": "华中理工大学按系招生　入学二三年后再定专业", "url": "http://data.people.com.cn/rmrb/pd.html?qs=%7B%22cds%22%3A%5B%7B%22cdr%22%3A%22AND%22%2C%22cds%22%3A%5B%7B%22fld%22%3A%22title%22%2C%22cdr%22%3A%22OR%22%2C%22hlt%22%3A%22true%22%2C%22vlr%22%3A%22OR%22%2C%22val%22%3A%22%E5%8D%8E%E4%B8%AD%E7%A7%91%E6%8A%80%E5%A4%A7%E5%AD%A6%22%7D%2C%7B%22fld%22%3A%22subTitle%22%2C%22cdr%22%3A%22OR%22%2C%22hlt%22%3A%22true%22%2C%22vlr%22%3A%22OR%22%2C%22val%22%3A%22%E5%8D%8E%E4%B8%AD%E7%A7%91%E6%8A%80%E5%A4%A7%E5%AD%A6%22%7D%2C%7B%22fld%22%3A%22introTitle%22%2C%22cdr%22%3A%22OR%22%2C%22hlt%22%3A%22true%22%2C%22vlr%22%3A%22OR%22%2C%22val%22%3A%22%E5%8D%8E%E4%B8%AD%E7%A7%91%E6%8A%80%E5%A4%A7%E5%AD%A6%22%7D%5D%7D%5D%2C%22obs%22%3A%5B%7B%22fld%22%3A%22dataTime%22%2C%22drt%22%3A%22DESC%22%7D%5D%7D&tr=A&pageNo=1&pageSize=500&position=146", "source": "1988年5月23日第3版"},
{"title": "华中理工大学改进毕业生思想教育", "url": "http://data.people.com.cn/rmrb/pd.html?qs=%7B%22cds%22%3A%5B%7B%22cdr%22%3A%22AND%22%2C%22cds%22%3A%5B%7B%22fld%22%3A%22title%22%2C%22cdr%22%3A%22OR%22%2C%22hlt%22%3A%22true%22%2C%22vlr%22%3A%22OR%22%2C%22val%22%3A%22%E5%8D%8E%E4%B8%AD%E7%A7%91%E6%8A%80%E5%A4%A7%E5%AD%A6%22%7D%2C%7B%22fld%22%3A%22subTitle%22%2C%22cdr%22%3A%22OR%22%2C%22hlt%22%3A%22true%22%2C%22vlr%22%3A%22OR%22%2C%22val%22%3A%22%E5%8D%8E%E4%B8%AD%E7%A7%91%E6%8A%80%E5%A4%A7%E5%AD%A6%22%7D%2C%7B%22fld%22%3A%22introTitle%22%2C%22cdr%22%3A%22OR%22%2C%22hlt%22%3A%22true%22%2C%22vlr%22%3A%22OR%22%2C%22val%22%3A%22%E5%8D%8E%E4%B8%AD%E7%A7%91%E6%8A%80%E5%A4%A7%E5%AD%A6%22%7D%5D%7D%5D%2C%22obs%22%3A%5B%7B%22fld%22%3A%22dataTime%22%2C%22drt%22%3A%22DESC%22%7D%5D%7D&tr=A&pageNo=1&pageSize=500&position=147", "source": "1988年2月25日第3版"},
{"title": "工人大学生回厂后发挥很大作用　　从华中工学院毕业的一批工人大学生，在生产岗位上，运用在大学所学的理论知识解决生产实际问题，受到工厂领导和群众的赞扬", "url": "http://data.people.com.cn/rmrb/pd.html?qs=%7B%22cds%22%3A%5B%7B%22cdr%22%3A%22AND%22%2C%22cds%22%3A%5B%7B%22fld%22%3A%22title%22%2C%22cdr%22%3A%22OR%22%2C%22hlt%22%3A%22true%22%2C%22vlr%22%3A%22OR%22%2C%22val%22%3A%22%E5%8D%8E%E4%B8%AD%E7%A7%91%E6%8A%80%E5%A4%A7%E5%AD%A6%22%7D%2C%7B%22fld%22%3A%22subTitle%22%2C%22cdr%22%3A%22OR%22%2C%22hlt%22%3A%22true%22%2C%22vlr%22%3A%22OR%22%2C%22val%22%3A%22%E5%8D%8E%E4%B8%AD%E7%A7%91%E6%8A%80%E5%A4%A7%E5%AD%A6%22%7D%2C%7B%22fld%22%3A%22introTitle%22%2C%22cdr%22%3A%22OR%22%2C%22hlt%22%3A%22true%22%2C%22vlr%22%3A%22OR%22%2C%22val%22%3A%22%E5%8D%8E%E4%B8%AD%E7%A7%91%E6%8A%80%E5%A4%A7%E5%AD%A6%22%7D%5D%7D%5D%2C%22obs%22%3A%5B%7B%22fld%22%3A%22dataTime%22%2C%22drt%22%3A%22DESC%22%7D%5D%7D&tr=A&pageNo=1&pageSize=500&position=184", "source": "1973年3月19日第1版"},
{"title": "武汉重型机床厂和华中工学院等联合办学的果实　    业余大学首届毕业生成绩优良", "url": "http://data.people.com.cn/rmrb/pd.html?qs=%7B%22cds%22%3A%5B%7B%22cdr%22%3A%22AND%22%2C%22cds%22%3A%5B%7B%22fld%22%3A%22title%22%2C%22cdr%22%3A%22OR%22%2C%22hlt%22%3A%22true%22%2C%22vlr%22%3A%22OR%22%2C%22val%22%3A%22%E5%8D%8E%E4%B8%AD%E7%A7%91%E6%8A%80%E5%A4%A7%E5%AD%A6%22%7D%2C%7B%22fld%22%3A%22subTitle%22%2C%22cdr%22%3A%22OR%22%2C%22hlt%22%3A%22true%22%2C%22vlr%22%3A%22OR%22%2C%22val%22%3A%22%E5%8D%8E%E4%B8%AD%E7%A7%91%E6%8A%80%E5%A4%A7%E5%AD%A6%22%7D%2C%7B%22fld%22%3A%22introTitle%22%2C%22cdr%22%3A%22OR%22%2C%22hlt%22%3A%22true%22%2C%22vlr%22%3A%22OR%22%2C%22val%22%3A%22%E5%8D%8E%E4%B8%AD%E7%A7%91%E6%8A%80%E5%A4%A7%E5%AD%A6%22%7D%5D%7D%5D%2C%22obs%22%3A%5B%7B%22fld%22%3A%22dataTime%22%2C%22drt%22%3A%22DESC%22%7D%5D%7D&tr=A&pageNo=1&pageSize=500&position=187", "source": "1961年12月13日第4版"}
]